[{"gender": "female", "groupShowType": "", "groupShowTopic": "", "country": "cn", "broadcastGender": "female", "genderGroup": "F", "previewUrlThumbSmall": "https://static-cdn.strpst.com/previews/8/1/4/8142a39aaea3f04cc67bf62cd6b45838-thumb-small", "username": "tingting66", "hlsPlaylist": "https://edge-hls.doppiocdn.com/hls/129981264/master/129981264_240p.m3u8", "snapshotServer": "eu4", "status": "public", "snapshotTimestamp": "1728899070", "broadcastSettings": {"width": 720, "height": 960}, "viewersCount": 1788, "topBestPlace": 0, "publicRecordingsRate": 150, "privateRate": 60, "popularSnapshotTimestamp": 1728898860, "spyRate": 24, "p2pRate": 90, "p2pVoiceRate": 0, "id": 129981264, "hasGroupShowAnnouncement": false, "isNonNude": false, "isHd": true, "isVr": false, "isMobile": true, "isNew": false, "isLive": true, "isOnline": true, "isRecommended": false, "isTagVerified": false, "isModel": true, "isRotated": false, "isLovense": true, "isKiiroo": false, "doSpy": true, "doPrivate": true, "streamName": "129981264", "presets": ["720p", "480p", "240p", "160p", "160p_blurred"]}, {"gender": "female", "groupShowType": "", "groupShowTopic": "", "country": "cn", "broadcastGender": "female", "avatarUrl": "https://static-cdn.strpst.com/avatars/6/1/e/61e87c2c4a4d457b125d98d61865e4f5-full", "genderGroup": "F", "previewUrlThumbSmall": "https://static-cdn.strpst.com/previews/4/8/2/4825bcb3f52279272624f836970f2340-thumb-small", "username": "Xixi-Gala", "hlsPlaylist": "https://edge-hls.doppiocdn.com/hls/171543165/master/171543165_240p.m3u8", "snapshotServer": "eu1", "status": "public", "snapshotTimestamp": "1728899070", "broadcastSettings": {"width": 720, "height": 960}, "viewersCount": 458, "topBestPlace": 0, "publicRecordingsRate": 60, "privateRate": 60, "popularSnapshotTimestamp": 1728898560, "spyRate": 16, "p2pRate": 90, "p2pVoiceRate": 0, "id": 171543165, "hasGroupShowAnnouncement": false, "isNonNude": false, "isHd": true, "isVr": false, "isMobile": true, "isNew": true, "isLive": true, "isOnline": true, "isRecommended": false, "isTagVerified": false, "isModel": true, "isRotated": false, "isLovense": true, "isKiiroo": false, "doSpy": true, "doPrivate": true, "isAvatarApproved": true, "streamName": "171543165", "presets": ["720p", "480p", "240p", "160p", "160p_blurred"]}, {"gender": "female", "groupShowType": "", "groupShowTopic": "", "country": "", "broadcastGender": "female", "avatarUrl": "https://static-cdn.strpst.com/avatars/7/8/3/783e4f871accc335553a532e9283ac89-full", "genderGroup": "F", "previewUrlThumbSmall": "https://static-cdn.strpst.com/previews/d/3/a/d3a10397f9b3841d7db5a533f5ee31fc-thumb-small", "username": "Ko_Alanna", "hlsPlaylist": "https://edge-hls.doppiocdn.com/hls/111375206/master/111375206_240p.m3u8", "snapshotServer": "eu1", "status": "public", "snapshotTimestamp": "1728899070", "broadcastSettings": {"width": 1280, "height": 720}, "viewersCount": 353, "topBestPlace": 21, "publicRecordingsRate": 150, "privateRate": 90, "popularSnapshotTimestamp": 1728898650, "spyRate": 44, "p2pRate": 150, "p2pVoiceRate": 0, "id": 111375206, "hasGroupShowAnnouncement": false, "isNonNude": false, "isHd": true, "isVr": false, "isMobile": false, "isNew": false, "isLive": true, "isOnline": true, "isRecommended": false, "isTagVerified": false, "isModel": true, "isRotated": false, "isLovense": true, "isKiiroo": false, "doSpy": true, "doPrivate": true, "isAvatarApproved": true, "streamName": "111375206", "presets": ["720p", "480p", "240p", "160p", "160p_blurred"]}, {"gender": "female", "groupShowType": "", "groupShowTopic": "", "country": "", "broadcastGender": "female", "avatarUrl": "https://static-cdn.strpst.com/avatars/9/2/5/9258265edc1bf2800fb1312ba8cd04e1-full", "genderGroup": "F", "previewUrlThumbSmall": "https://static-cdn.strpst.com/previews/0/1/1/011fbf97d3121fd9226040d90dcfdc90-thumb-small", "username": "takeoffformoney", "hlsPlaylist": "https://edge-hls.doppiocdn.com/hls/163265103/master/163265103_240p.m3u8", "snapshotServer": "eu12", "status": "public", "snapshotTimestamp": "1728899070", "broadcastSettings": {"width": 1920, "height": 1080}, "viewersCount": 268, "topBestPlace": 0, "publicRecordingsRate": 8, "privateRate": 90, "popularSnapshotTimestamp": 0, "spyRate": 44, "p2pRate": 120, "p2pVoiceRate": 0, "id": 163265103, "hasGroupShowAnnouncement": false, "isNonNude": false, "isHd": true, "isVr": false, "isMobile": false, "isNew": false, "isLive": true, "isOnline": true, "isRecommended": false, "isTagVerified": false, "isModel": true, "isRotated": false, "isLovense": true, "isKiiroo": false, "doSpy": true, "doPrivate": true, "isAvatarApproved": true, "streamName": "163265103", "presets": ["1080p60", "720p60", "720p", "480p", "240p", "160p", "160p_blurred"]}, {"gender": "female", "groupShowType": "", "groupShowTopic": "", "country": "cn", "broadcastGender": "female", "avatarUrl": "https://static-cdn.strpst.com/avatars/5/0/c/50c23819cdd59b8f7416fef6c4fbbf9a-full", "genderGroup": "F", "previewUrlThumbSmall": "https://static-cdn.strpst.com/previews/7/f/f/7ff1f1f60e66f515c5c58611f8836609-thumb-small", "username": "CaTT-ToT", "hlsPlaylist": "https://edge-hls.doppiocdn.com/hls/172827802/master/172827802_240p.m3u8", "snapshotServer": "eu12", "status": "public", "snapshotTimestamp": "1728899070", "broadcastSettings": {"width": 1280, "height": 720}, "viewersCount": 179, "topBestPlace": 0, "publicRecordingsRate": 150, "privateRate": 60, "popularSnapshotTimestamp": 1728898950, "spyRate": 32, "p2pRate": 90, "p2pVoiceRate": 0, "id": 172827802, "hasGroupShowAnnouncement": false, "isNonNude": false, "isHd": true, "isVr": false, "isMobile": false, "isNew": false, "isLive": true, "isOnline": true, "isRecommended": false, "isTagVerified": false, "isModel": true, "isRotated": false, "isLovense": true, "isKiiroo": false, "doSpy": true, "doPrivate": true, "isAvatarApproved": true, "streamName": "172827802", "presets": ["480p", "240p", "160p", "160p_blurred"]}, {"gender": "females", "groupShowType": "ticket", "groupShowTopic": "4\u5973\u8f6e\u6d41\u55b7\u6cc9\u6492\u6c34 \u63d2\u903c\u903c\u7279\u5199", "country": "", "broadcastGender": "group", "avatarUrl": "https://static-cdn.strpst.com/avatars/b/c/1/bc1ff1c1acdee365a495de9679725cfd-full", "genderGroup": "F", "previewUrlThumbSmall": "https://static-cdn.strpst.com/previews/2/a/d/2ad5d19bf1debde6042047ef58a92715-thumb-small", "username": "smm555", "hlsPlaylist": "https://edge-hls.doppiocdn.com/hls/165829792/master/165829792_240p.m3u8", "snapshotServer": "eu4", "status": "groupShow", "snapshotTimestamp": "1728899070", "broadcastSettings": {"width": 1920, "height": 1080}, "viewersCount": 158, "topBestPlace": 0, "publicRecordingsRate": 16, "privateRate": 0, "popularSnapshotTimestamp": 1728898410, "spyRate": 0, "p2pRate": 0, "p2pVoiceRate": 0, "id": 165829792, "hasGroupShowAnnouncement": false, "isNonNude": false, "isHd": true, "isVr": false, "isMobile": false, "isNew": false, "isLive": true, "isOnline": true, "isRecommended": false, "isTagVerified": false, "isModel": true, "isRotated": false, "isLovense": true, "isKiiroo": false, "doSpy": false, "doPrivate": false, "isAvatarApproved": true, "streamName": "165829792", "presets": ["1080p", "720p", "480p", "240p", "160p", "160p_blurred"]}, {"gender": "female", "groupShowType": "", "groupShowTopic": "", "country": "", "broadcastGender": "female", "avatarUrl": "https://static-cdn.strpst.com/avatars/8/f/c/8fc862d56f4c06e4c11f0dc43712da8f-full", "genderGroup": "F", "previewUrlThumbSmall": "https://static-cdn.strpst.com/previews/b/c/0/bc08f2921a6f7af8983f6e8e72bb4fec-thumb-small", "username": "CaTToiin_", "hlsPlaylist": "https://edge-hls.doppiocdn.com/hls/167905607/master/167905607_240p.m3u8", "snapshotServer": "eu2", "status": "public", "snapshotTimestamp": "1728899070", "broadcastSettings": {"width": 1280, "height": 720}, "viewersCount": 149, "topBestPlace": 0, "publicRecordingsRate": 150, "privateRate": 90, "popularSnapshotTimestamp": 1728898950, "spyRate": 60, "p2pRate": 120, "p2pVoiceRate": 0, "id": 167905607, "hasGroupShowAnnouncement": false, "isNonNude": false, "isHd": true, "isVr": false, "isMobile": false, "isNew": false, "isLive": true, "isOnline": true, "isRecommended": false, "isTagVerified": false, "isModel": true, "isRotated": false, "isLovense": true, "isKiiroo": false, "doSpy": true, "doPrivate": true, "isAvatarApproved": true, "streamName": "167905607", "presets": ["720p", "480p", "240p", "160p", "160p_blurred"]}, {"gender": "females", "groupShowType": "", "groupShowTopic": "", "country": "", "broadcastGender": "female", "avatarUrl": "https://static-cdn.strpst.com/avatars/2/0/4/2049ccac4cecde5bcca3f57f15a6480f-full", "genderGroup": "F", "previewUrlThumbSmall": "https://static-cdn.strpst.com/previews/8/a/d/8ad2f7967de5414be9ea53edba5ebbb4-thumb-small", "username": "Ledo-888", "hlsPlaylist": "https://edge-hls.doppiocdn.com/hls/163925064/master/163925064.m3u8", "snapshotServer": "eu11", "status": "public", "snapshotTimestamp": "1728899070", "broadcastSettings": {"width": 864, "height": 480}, "viewersCount": 145, "topBestPlace": 0, "publicRecordingsRate": 150, "privateRate": 200, "popularSnapshotTimestamp": 1728898200, "spyRate": 60, "p2pRate": 150, "p2pVoiceRate": 0, "id": 163925064, "hasGroupShowAnnouncement": false, "isNonNude": false, "isHd": false, "isVr": false, "isMobile": false, "isNew": false, "isLive": true, "isOnline": true, "isRecommended": false, "isTagVerified": false, "isModel": true, "isRotated": false, "isLovense": true, "isKiiroo": false, "doSpy": true, "doPrivate": true, "isAvatarApproved": true, "streamName": "163925064", "presets": null}, {"gender": "female", "groupShowType": "", "groupShowTopic": "", "country": "", "broadcastGender": "female", "avatarUrl": "https://static-cdn.strpst.com/avatars/d/9/9/d99cce77854f55bc6900a51c3dff2965-full", "genderGroup": "F", "previewUrlThumbSmall": "https://static-cdn.strpst.com/previews/7/d/3/7d31b3c2fd2d6caf8f8d3f00917e2f36-thumb-small", "username": "Southerly", "hlsPlaylist": "https://edge-hls.doppiocdn.com/hls/93936177/master/93936177_240p.m3u8", "snapshotServer": "eu12", "status": "public", "snapshotTimestamp": "1728899070", "broadcastSettings": {"width": 1280, "height": 720}, "viewersCount": 144, "topBestPlace": 0, "publicRecordingsRate": 150, "privateRate": 60, "popularSnapshotTimestamp": 1728898410, "spyRate": 44, "p2pRate": 90, "p2pVoiceRate": 0, "id": 93936177, "hasGroupShowAnnouncement": false, "isNonNude": false, "isHd": true, "isVr": false, "isMobile": false, "isNew": false, "isLive": true, "isOnline": true, "isRecommended": false, "isTagVerified": false, "isModel": true, "isRotated": false, "isLovense": true, "isKiiroo": false, "doSpy": true, "doPrivate": true, "isAvatarApproved": true, "streamName": "93936177", "presets": ["720p", "480p", "240p", "160p", "160p_blurred"]}, {"gender": "female", "groupShowType": "", "groupShowTopic": "", "country": "", "broadcastGender": "female", "avatarUrl": "https://static-cdn.strpst.com/avatars/3/4/e/34e5720b6535bfecfc8ab8998814235d-full", "genderGroup": "F", "previewUrlThumbSmall": "https://static-cdn.strpst.com/previews/4/4/4/44451044bce1bf7f4ea36bcc629c8305-thumb-small", "username": "rue6", "hlsPlaylist": "https://edge-hls.doppiocdn.com/hls/147223979/master/147223979_240p.m3u8", "snapshotServer": "eu12", "status": "public", "snapshotTimestamp": "1728899070", "broadcastSettings": {"width": 1280, "height": 720}, "viewersCount": 141, "topBestPlace": 0, "publicRecordingsRate": 60, "privateRate": 60, "popularSnapshotTimestamp": 1728898410, "spyRate": 60, "p2pRate": 90, "p2pVoiceRate": 0, "id": 147223979, "hasGroupShowAnnouncement": false, "isNonNude": false, "isHd": true, "isVr": false, "isMobile": false, "isNew": false, "isLive": true, "isOnline": true, "isRecommended": false, "isTagVerified": false, "isModel": true, "isRotated": false, "isLovense": true, "isKiiroo": false, "doSpy": true, "doPrivate": true, "isAvatarApproved": true, "streamName": "147223979", "presets": ["720p60", "480p", "240p", "160p", "160p_blurred"]}, {"gender": "female", "groupShowType": "", "groupShowTopic": "", "country": "", "broadcastGender": "female", "avatarUrl": "https://static-cdn.strpst.com/avatars/1/a/f/1af78fa3c834b8bfa10fad1856222596-full", "genderGroup": "F", "previewUrlThumbSmall": "https://static-cdn.strpst.com/previews/f/d/e/fdede44fabf8c6bee0fd126ce46fb91c-thumb-small", "username": "ENNA_999", "hlsPlaylist": "https://edge-hls.doppiocdn.com/hls/151561964/master/151561964.m3u8", "snapshotServer": "eu2", "status": "public", "snapshotTimestamp": "1728899070", "broadcastSettings": {"width": 640, "height": 360}, "viewersCount": 117, "topBestPlace": 0, "publicRecordingsRate": 8, "privateRate": 90, "popularSnapshotTimestamp": 1728898410, "spyRate": 60, "p2pRate": 120, "p2pVoiceRate": 0, "id": 151561964, "hasGroupShowAnnouncement": false, "isNonNude": false, "isHd": false, "isVr": false, "isMobile": false, "isNew": false, "isLive": true, "isOnline": true, "isRecommended": false, "isTagVerified": false, "isModel": true, "isRotated": false, "isLovense": true, "isKiiroo": false, "doSpy": true, "doPrivate": true, "isAvatarApproved": true, "streamName": "151561964", "presets": null}, {"gender": "female", "groupShowType": "", "groupShowTopic": "", "country": "", "broadcastGender": "female", "avatarUrl": "https://static-cdn.strpst.com/avatars/1/9/2/192285a097538d6c7ce6ca7c9f275e98-full", "genderGroup": "F", "previewUrlThumbSmall": "https://static-cdn.strpst.com/previews/5/a/0/5a0bbf460705e9d96377dadc419ad4fb-thumb-small", "username": "Krismil3", "hlsPlaylist": "https://edge-hls.doppiocdn.com/hls/164673862/master/164673862_240p.m3u8", "snapshotServer": "eu11", "status": "public", "snapshotTimestamp": "1728899070", "broadcastSettings": {"width": 1280, "height": 720}, "viewersCount": 114, "topBestPlace": 0, "publicRecordingsRate": 150, "privateRate": 60, "popularSnapshotTimestamp": 1728898650, "spyRate": 60, "p2pRate": 90, "p2pVoiceRate": 0, "id": 164673862, "hasGroupShowAnnouncement": false, "isNonNude": false, "isHd": true, "isVr": false, "isMobile": false, "isNew": false, "isLive": true, "isOnline": true, "isRecommended": false, "isTagVerified": false, "isModel": true, "isRotated": false, "isLovense": true, "isKiiroo": false, "doSpy": true, "doPrivate": true, "isAvatarApproved": true, "streamName": "164673862", "presets": ["720p60", "480p", "240p", "160p", "160p_blurred"]}, {"gender": "maleFemale", "groupShowType": "", "groupShowTopic": "", "country": "", "broadcastGender": "group", "avatarUrl": "https://static-cdn.strpst.com/avatars/2/6/8/26847c1ded582771c3e07f38fadd95e2-full", "genderGroup": "F", "previewUrlThumbSmall": "https://static-cdn.strpst.com/previews/f/7/e/f7ea81a53b21486266a1d6b99004680e-thumb-small", "username": "xiaoyusan", "hlsPlaylist": "https://edge-hls.doppiocdn.com/hls/150487583/master/150487583_240p.m3u8", "snapshotServer": "eu8", "status": "public", "snapshotTimestamp": "1728899070", "broadcastSettings": {"width": 1280, "height": 720}, "viewersCount": 109, "topBestPlace": 0, "publicRecordingsRate": 150, "privateRate": 32, "popularSnapshotTimestamp": 1728898830, "spyRate": 16, "p2pRate": 32, "p2pVoiceRate": 0, "id": 150487583, "hasGroupShowAnnouncement": false, "isNonNude": false, "isHd": true, "isVr": false, "isMobile": false, "isNew": false, "isLive": true, "isOnline": true, "isRecommended": false, "isTagVerified": false, "isModel": true, "isRotated": false, "isLovense": false, "isKiiroo": false, "doSpy": true, "doPrivate": true, "isAvatarApproved": true, "streamName": "150487583", "presets": ["720p", "480p", "240p", "160p", "160p_blurred"]}, {"gender": "females", "groupShowType": "", "groupShowTopic": "", "country": "", "broadcastGender": "group", "avatarUrl": "https://static-cdn.strpst.com/avatars/0/8/8/08862acba06755dffadbd7fc6d2e128a-full", "genderGroup": "F", "previewUrlThumbSmall": "https://static-cdn.strpst.com/previews/c/6/a/c6a6a28fac28b059262d4f26302a10c3-thumb-small", "username": "MiMiGouGou-666", "hlsPlaylist": "https://edge-hls.doppiocdn.com/hls/169265255/master/169265255_240p.m3u8", "snapshotServer": "eu10", "status": "public", "snapshotTimestamp": "1728899070", "broadcastSettings": {"width": 1280, "height": 720}, "viewersCount": 108, "topBestPlace": 0, "publicRecordingsRate": 32, "privateRate": 120, "popularSnapshotTimestamp": 1728898500, "spyRate": 60, "p2pRate": 150, "p2pVoiceRate": 0, "id": 169265255, "hasGroupShowAnnouncement": false, "isNonNude": false, "isHd": true, "isVr": false, "isMobile": false, "isNew": false, "isLive": true, "isOnline": true, "isRecommended": false, "isTagVerified": false, "isModel": true, "isRotated": false, "isLovense": true, "isKiiroo": false, "doSpy": true, "doPrivate": true, "isAvatarApproved": true, "streamName": "169265255", "presets": ["720p", "480p", "240p", "160p", "160p_blurred"]}, {"gender": "female", "groupShowType": "", "groupShowTopic": "", "country": "", "broadcastGender": "female", "avatarUrl": "https://static-cdn.strpst.com/avatars/8/e/3/8e3c4f0d5a91d9417b82f81829740d56-full", "genderGroup": "F", "previewUrlThumbSmall": "https://static-cdn.strpst.com/previews/6/1/4/614d0e6ec0b5344ef2796439d6213f72-thumb-small", "username": "miaomijiang", "hlsPlaylist": "https://edge-hls.doppiocdn.com/hls/137025934/master/137025934_240p.m3u8", "snapshotServer": "eu12", "status": "public", "snapshotTimestamp": "1728899070", "broadcastSettings": {"width": 1280, "height": 720}, "viewersCount": 103, "topBestPlace": 0, "publicRecordingsRate": 150, "privateRate": 32, "popularSnapshotTimestamp": 1728898650, "spyRate": 32, "p2pRate": 60, "p2pVoiceRate": 0, "id": 137025934, "hasGroupShowAnnouncement": false, "isNonNude": false, "isHd": true, "isVr": false, "isMobile": false, "isNew": false, "isLive": true, "isOnline": true, "isRecommended": false, "isTagVerified": false, "isModel": true, "isRotated": false, "isLovense": true, "isKiiroo": false, "doSpy": true, "doPrivate": true, "isAvatarApproved": true, "streamName": "137025934", "presets": ["720p", "480p", "240p", "160p", "160p_blurred"]}, {"gender": "female", "groupShowType": "", "groupShowTopic": "", "country": "", "broadcastGender": "female", "avatarUrl": "https://static-cdn.strpst.com/avatars/4/4/6/4469e6a515abd3bc0da4d333913ff3a7-full", "genderGroup": "F", "previewUrlThumbSmall": "https://static-cdn.strpst.com/previews/e/6/1/e611b33c934a0177d56cdf99d0f00a3c-thumb-small", "username": "Aurora_99", "hlsPlaylist": "https://edge-hls.doppiocdn.com/hls/121228369/master/121228369_240p.m3u8", "snapshotServer": "eu8", "status": "public", "snapshotTimestamp": "1728899070", "broadcastSettings": {"width": 1920, "height": 1080}, "viewersCount": 92, "topBestPlace": 0, "publicRecordingsRate": 150, "privateRate": 60, "popularSnapshotTimestamp": 1728898200, "spyRate": 60, "p2pRate": 90, "p2pVoiceRate": 0, "id": 121228369, "hasGroupShowAnnouncement": false, "isNonNude": false, "isHd": true, "isVr": false, "isMobile": false, "isNew": false, "isLive": true, "isOnline": true, "isRecommended": false, "isTagVerified": false, "isModel": true, "isRotated": false, "isLovense": true, "isKiiroo": false, "doSpy": true, "doPrivate": true, "isAvatarApproved": true, "streamName": "121228369", "presets": ["1080p", "720p", "480p", "240p", "160p", "160p_blurred"]}, {"gender": "female", "groupShowType": "", "groupShowTopic": "", "country": "", "broadcastGender": "female", "genderGroup": "F", "previewUrlThumbSmall": "https://static-cdn.strpst.com/previews/a/9/d/a9da90bce6f83dc2d380a6bb6855c7fc-thumb-small", "username": "rose-u", "hlsPlaylist": "https://edge-hls.doppiocdn.com/hls/106129912/master/106129912_240p.m3u8", "snapshotServer": "eu10", "status": "public", "snapshotTimestamp": "1728899070", "broadcastSettings": {"width": 720, "height": 960}, "viewersCount": 91, "topBestPlace": 0, "publicRecordingsRate": 8, "privateRate": 90, "popularSnapshotTimestamp": 1728898260, "spyRate": 60, "p2pRate": 150, "p2pVoiceRate": 0, "id": 106129912, "hasGroupShowAnnouncement": false, "isNonNude": false, "isHd": true, "isVr": false, "isMobile": true, "isNew": false, "isLive": true, "isOnline": true, "isRecommended": false, "isTagVerified": false, "isModel": true, "isRotated": false, "isLovense": true, "isKiiroo": false, "doSpy": true, "doPrivate": true, "streamName": "106129912", "presets": ["720p", "480p", "240p", "160p", "160p_blurred"]}, {"gender": "female", "groupShowType": "", "groupShowTopic": "", "country": "", "broadcastGender": "female", "avatarUrl": "https://static-cdn.strpst.com/avatars/f/0/b/f0be78d3a5b8a3bc43051bcbda144eb1-full", "genderGroup": "F", "previewUrlThumbSmall": "https://static-cdn.strpst.com/previews/a/c/7/ac78a1cf76984a07b318edc48bdd5ee8-thumb-small", "username": "L-Moonlight", "hlsPlaylist": "https://edge-hls.doppiocdn.com/hls/163695296/master/163695296_240p.m3u8", "snapshotServer": "eu5", "status": "public", "snapshotTimestamp": "1728899070", "broadcastSettings": {"width": 1920, "height": 1080}, "viewersCount": 89, "topBestPlace": 14, "publicRecordingsRate": 60, "privateRate": 90, "popularSnapshotTimestamp": 1728898290, "spyRate": 60, "p2pRate": 200, "p2pVoiceRate": 0, "id": 163695296, "hasGroupShowAnnouncement": false, "isNonNude": false, "isHd": true, "isVr": false, "isMobile": false, "isNew": false, "isLive": true, "isOnline": true, "isRecommended": false, "isTagVerified": false, "isModel": true, "isRotated": false, "isLovense": true, "isKiiroo": false, "doSpy": true, "doPrivate": true, "isAvatarApproved": true, "streamName": "163695296", "presets": ["1080p", "720p", "480p", "240p", "160p", "160p_blurred"]}, {"gender": "female", "groupShowType": "", "groupShowTopic": "", "country": "", "broadcastGender": "female", "avatarUrl": "https://static-cdn.strpst.com/avatars/9/9/4/994a6d92bc484f91ce84dee2fb2e1486-full", "genderGroup": "F", "previewUrlThumbSmall": "https://static-cdn.strpst.com/previews/7/c/a/7ca44546d220ec6862a1d45990855392-thumb-small", "username": "Mia826", "hlsPlaylist": "https://edge-hls.doppiocdn.com/hls/169138603/master/169138603.m3u8", "snapshotServer": "eu4", "status": "public", "snapshotTimestamp": "1728899070", "broadcastSettings": {"width": 864, "height": 480}, "viewersCount": 82, "topBestPlace": 19, "publicRecordingsRate": 8, "privateRate": 90, "popularSnapshotTimestamp": 1728898950, "spyRate": 60, "p2pRate": 120, "p2pVoiceRate": 0, "id": 169138603, "hasGroupShowAnnouncement": false, "isNonNude": false, "isHd": false, "isVr": false, "isMobile": false, "isNew": false, "isLive": true, "isOnline": true, "isRecommended": false, "isTagVerified": false, "isModel": true, "isRotated": false, "isLovense": false, "isKiiroo": false, "doSpy": true, "doPrivate": true, "isAvatarApproved": true, "streamName": "169138603", "presets": null}, {"gender": "female", "groupShowType": "", "groupShowTopic": "", "country": "", "broadcastGender": "female", "avatarUrl": "https://static-cdn.strpst.com/avatars/a/3/2/a3284aa8135e30d3022e4a30954b0d1b-full", "genderGroup": "F", "previewUrlThumbSmall": "https://static-cdn.strpst.com/previews/9/6/4/964992691c83f66bd64ed8f13968820b-thumb-small", "username": "Mini-X", "hlsPlaylist": "https://edge-hls.doppiocdn.com/hls/160449681/master/160449681_240p.m3u8", "snapshotServer": "eu7", "status": "public", "snapshotTimestamp": "1728899070", "broadcastSettings": {"width": 1280, "height": 720}, "viewersCount": 68, "topBestPlace": 0, "publicRecordingsRate": 8, "privateRate": 90, "popularSnapshotTimestamp": 1728898680, "spyRate": 44, "p2pRate": 120, "p2pVoiceRate": 0, "id": 160449681, "hasGroupShowAnnouncement": false, "isNonNude": false, "isHd": true, "isVr": false, "isMobile": false, "isNew": false, "isLive": true, "isOnline": true, "isRecommended": false, "isTagVerified": false, "isModel": true, "isRotated": false, "isLovense": true, "isKiiroo": false, "doSpy": true, "doPrivate": true, "isAvatarApproved": true, "streamName": "160449681", "presets": ["720p", "480p", "240p", "160p", "160p_blurred"]}, {"gender": "females", "groupShowType": "", "groupShowTopic": "", "country": "", "broadcastGender": "group", "avatarUrl": "https://static-cdn.strpst.com/avatars/7/9/1/7914ed6310941ddb64d224f528195e54-full", "genderGroup": "F", "previewUrlThumbSmall": "https://static-cdn.strpst.com/previews/9/d/3/9d3b252f9cfbaf8a5b8d6901fa14ead2-thumb-small", "username": "Red-SweetGirl", "hlsPlaylist": "https://edge-hls.doppiocdn.com/hls/172085735/master/172085735_240p.m3u8", "snapshotServer": "eu11", "status": "public", "snapshotTimestamp": "1728899070", "broadcastSettings": {"width": 1280, "height": 720}, "viewersCount": 56, "topBestPlace": 0, "publicRecordingsRate": 8, "privateRate": 0, "popularSnapshotTimestamp": 1728898380, "spyRate": 0, "p2pRate": 0, "p2pVoiceRate": 0, "id": 172085735, "hasGroupShowAnnouncement": false, "isNonNude": false, "isHd": true, "isVr": false, "isMobile": false, "isNew": false, "isLive": true, "isOnline": true, "isRecommended": false, "isTagVerified": false, "isModel": true, "isRotated": false, "isLovense": false, "isKiiroo": false, "doSpy": false, "doPrivate": false, "isAvatarApproved": true, "streamName": "172085735", "presets": ["720p60", "480p", "240p", "160p", "160p_blurred"]}, {"gender": "female", "groupShowType": "", "groupShowTopic": "", "country": "", "broadcastGender": "female", "avatarUrl": "https://static-cdn.strpst.com/avatars/2/9/b/29bb7876247bc08d8b066fff81078174-full", "genderGroup": "F", "previewUrlThumbSmall": "https://static-cdn.strpst.com/previews/4/5/4/454c825f58918b80fb99717e1971cf7e-thumb-small", "username": "Zhi-Shi", "hlsPlaylist": "https://edge-hls.doppiocdn.com/hls/167976431/master/167976431_240p.m3u8", "snapshotServer": "eu3", "status": "public", "snapshotTimestamp": "1728899070", "broadcastSettings": {"width": 1280, "height": 720}, "viewersCount": 56, "topBestPlace": 0, "publicRecordingsRate": 150, "privateRate": 60, "popularSnapshotTimestamp": 1728898290, "spyRate": 60, "p2pRate": 120, "p2pVoiceRate": 0, "id": 167976431, "hasGroupShowAnnouncement": false, "isNonNude": false, "isHd": true, "isVr": false, "isMobile": false, "isNew": false, "isLive": true, "isOnline": true, "isRecommended": false, "isTagVerified": false, "isModel": true, "isRotated": false, "isLovense": true, "isKiiroo": false, "doSpy": true, "doPrivate": true, "isAvatarApproved": true, "streamName": "167976431", "presets": ["480p", "240p", "160p", "160p_blurred"]}, {"gender": "female", "groupShowType": "", "groupShowTopic": "", "country": "cn", "broadcastGender": "female", "avatarUrl": "https://static-cdn.strpst.com/avatars/2/2/5/225e12bfbdb5c7be17c7712b94d324e4-full", "genderGroup": "F", "previewUrlThumbSmall": "https://static-cdn.strpst.com/previews/2/e/3/2e35c38d0465ac2bf1ff350be8d2d8f1-thumb-small", "username": "Lily0709", "hlsPlaylist": "https://edge-hls.doppiocdn.com/hls/171762148/master/171762148_240p.m3u8", "snapshotServer": "eu2", "status": "public", "snapshotTimestamp": "1728899070", "broadcastSettings": {"width": 1920, "height": 1080}, "viewersCount": 54, "topBestPlace": 0, "publicRecordingsRate": 150, "privateRate": 60, "popularSnapshotTimestamp": 1728898350, "spyRate": 0, "p2pRate": 90, "p2pVoiceRate": 0, "id": 171762148, "hasGroupShowAnnouncement": false, "isNonNude": false, "isHd": true, "isVr": false, "isMobile": false, "isNew": false, "isLive": true, "isOnline": true, "isRecommended": false, "isTagVerified": false, "isModel": true, "isRotated": false, "isLovense": true, "isKiiroo": false, "doSpy": false, "doPrivate": true, "isAvatarApproved": true, "streamName": "171762148", "presets": ["1080p", "720p", "480p", "240p", "160p", "160p_blurred"]}, {"gender": "female", "groupShowType": "", "groupShowTopic": "", "country": "", "broadcastGender": "female", "avatarUrl": "https://static-cdn.strpst.com/avatars/5/4/7/54734148c14122815483e33a6d0faba6-full", "genderGroup": "F", "previewUrlThumbSmall": "https://static-cdn.strpst.com/previews/9/1/4/9141eaa30cbb188949e37871e627ea17-thumb-small", "username": "Fan1212__", "hlsPlaylist": "https://edge-hls.doppiocdn.com/hls/171763359/master/171763359_240p.m3u8", "snapshotServer": "eu12", "status": "public", "snapshotTimestamp": "1728899070", "broadcastSettings": {"width": 1280, "height": 720}, "viewersCount": 50, "topBestPlace": 0, "publicRecordingsRate": 8, "privateRate": 60, "popularSnapshotTimestamp": 1728898500, "spyRate": 60, "p2pRate": 90, "p2pVoiceRate": 0, "id": 171763359, "hasGroupShowAnnouncement": false, "isNonNude": false, "isHd": true, "isVr": false, "isMobile": false, "isNew": false, "isLive": true, "isOnline": true, "isRecommended": false, "isTagVerified": false, "isModel": true, "isRotated": false, "isLovense": true, "isKiiroo": false, "doSpy": true, "doPrivate": true, "isAvatarApproved": true, "streamName": "171763359", "presets": ["720p60", "480p", "240p", "160p", "160p_blurred"]}, {"gender": "female", "groupShowType": "", "groupShowTopic": "", "country": "", "broadcastGender": "female", "avatarUrl": "https://static-cdn.strpst.com/avatars/2/2/e/22ec32b4b66d1f482eb8ef6d635ef8fc-full", "genderGroup": "F", "previewUrlThumbSmall": "https://static-cdn.strpst.com/previews/5/5/f/55fc6cd04b3f58afac306aa525aec586-thumb-small", "username": "palzkybi123", "hlsPlaylist": "https://edge-hls.doppiocdn.com/hls/141325849/master/141325849_240p.m3u8", "snapshotServer": "eu5", "status": "public", "snapshotTimestamp": "1728899070", "broadcastSettings": {"width": 720, "height": 960}, "viewersCount": 48, "topBestPlace": 0, "publicRecordingsRate": 8, "privateRate": 60, "popularSnapshotTimestamp": 1728898620, "spyRate": 24, "p2pRate": 90, "p2pVoiceRate": 0, "id": 141325849, "hasGroupShowAnnouncement": false, "isNonNude": false, "isHd": true, "isVr": false, "isMobile": true, "isNew": false, "isLive": true, "isOnline": true, "isRecommended": false, "isTagVerified": false, "isModel": true, "isRotated": false, "isLovense": true, "isKiiroo": false, "doSpy": true, "doPrivate": true, "isAvatarApproved": true, "streamName": "141325849", "presets": ["480p", "240p", "160p", "160p_blurred"]}, {"gender": "female", "groupShowType": "", "groupShowTopic": "", "country": "", "broadcastGender": "female", "avatarUrl": "https://static-cdn.strpst.com/avatars/1/6/6/166809474f244e30f166a363eb988dc1-full", "genderGroup": "F", "previewUrlThumbSmall": "https://static-cdn.strpst.com/previews/6/3/5/635e2c67e0f067f98a32bfaf83a82abf-thumb-small", "username": "bendandawang", "hlsPlaylist": "https://edge-hls.doppiocdn.com/hls/166839455/master/166839455_240p.m3u8", "snapshotServer": "eu5", "status": "public", "snapshotTimestamp": "1728899070", "broadcastSettings": {"width": 1280, "height": 720}, "viewersCount": 45, "topBestPlace": 0, "publicRecordingsRate": 8, "privateRate": 200, "popularSnapshotTimestamp": 1728898290, "spyRate": 60, "p2pRate": 120, "p2pVoiceRate": 0, "id": 166839455, "hasGroupShowAnnouncement": false, "isNonNude": false, "isHd": true, "isVr": false, "isMobile": false, "isNew": false, "isLive": true, "isOnline": false, "isRecommended": false, "isTagVerified": false, "isModel": true, "isRotated": false, "isLovense": false, "isKiiroo": false, "doSpy": true, "doPrivate": true, "isAvatarApproved": true, "streamName": "166839455", "presets": ["480p", "240p", "160p", "160p_blurred"]}, {"gender": "female", "groupShowType": "", "groupShowTopic": "", "country": "", "broadcastGender": "female", "avatarUrl": "https://static-cdn.strpst.com/avatars/9/a/f/9af057f6a4ea2048b2a34c46823c0cf7-full", "genderGroup": "F", "previewUrlThumbSmall": "https://static-cdn.strpst.com/previews/a/d/d/add9087d19d907f76c137468452f2eae-thumb-small", "username": "GGmm-ii", "hlsPlaylist": "https://edge-hls.doppiocdn.com/hls/168797525/master/168797525_240p.m3u8", "snapshotServer": "eu8", "status": "public", "snapshotTimestamp": "1728899070", "broadcastSettings": {"width": 1280, "height": 720}, "viewersCount": 44, "topBestPlace": 0, "publicRecordingsRate": 8, "privateRate": 60, "popularSnapshotTimestamp": 1728898650, "spyRate": 60, "p2pRate": 90, "p2pVoiceRate": 0, "id": 168797525, "hasGroupShowAnnouncement": false, "isNonNude": false, "isHd": true, "isVr": false, "isMobile": false, "isNew": false, "isLive": true, "isOnline": true, "isRecommended": false, "isTagVerified": false, "isModel": true, "isRotated": false, "isLovense": true, "isKiiroo": false, "doSpy": true, "doPrivate": true, "isAvatarApproved": true, "streamName": "168797525", "presets": ["720p", "480p", "240p", "160p", "160p_blurred"]}, {"gender": "females", "groupShowType": "", "groupShowTopic": "", "country": "", "broadcastGender": "female", "avatarUrl": "https://static-cdn.strpst.com/avatars/a/9/c/a9cce372b7aadd9ad13deba2b5d9dc4f-full", "genderGroup": "F", "previewUrlThumbSmall": "https://static-cdn.strpst.com/previews/b/a/b/bab8c373464865e3e0b41a248b93c31f-thumb-small", "username": "Alice-821", "hlsPlaylist": "https://edge-hls.doppiocdn.com/hls/162789401/master/162789401.m3u8", "snapshotServer": "eu6", "status": "public", "snapshotTimestamp": "1728899070", "broadcastSettings": {"width": 960, "height": 540}, "viewersCount": 44, "topBestPlace": 0, "publicRecordingsRate": 150, "privateRate": 0, "popularSnapshotTimestamp": 1728898890, "spyRate": 0, "p2pRate": 120, "p2pVoiceRate": 0, "id": 162789401, "hasGroupShowAnnouncement": false, "isNonNude": false, "isHd": false, "isVr": false, "isMobile": false, "isNew": false, "isLive": true, "isOnline": true, "isRecommended": false, "isTagVerified": false, "isModel": true, "isRotated": false, "isLovense": true, "isKiiroo": false, "doSpy": false, "doPrivate": false, "isAvatarApproved": true, "streamName": "162789401", "presets": null}, {"gender": "female", "groupShowType": "", "groupShowTopic": "", "country": "", "broadcastGender": "female", "genderGroup": "F", "previewUrlThumbSmall": "https://static-cdn.strpst.com/previews/b/9/c/b9c12c6dcf9b5def65ae14e955b5f6e0-thumb-small", "username": "Niannian-sexy", "hlsPlaylist": "https://edge-hls.doppiocdn.com/hls/173159730/master/173159730_240p.m3u8", "snapshotServer": "eu10", "status": "public", "snapshotTimestamp": "1728899070", "broadcastSettings": {"width": 1280, "height": 720}, "viewersCount": 43, "topBestPlace": 0, "publicRecordingsRate": 150, "privateRate": 60, "popularSnapshotTimestamp": 1728898830, "spyRate": 60, "p2pRate": 90, "p2pVoiceRate": 0, "id": 173159730, "hasGroupShowAnnouncement": false, "isNonNude": false, "isHd": true, "isVr": false, "isMobile": false, "isNew": true, "isLive": true, "isOnline": true, "isRecommended": false, "isTagVerified": false, "isModel": true, "isRotated": false, "isLovense": true, "isKiiroo": false, "doSpy": true, "doPrivate": true, "streamName": "173159730", "presets": ["480p", "240p", "160p", "160p_blurred"]}, {"gender": "female", "groupShowType": "", "groupShowTopic": "", "country": "", "broadcastGender": "female", "avatarUrl": "https://static-cdn.strpst.com/avatars/e/0/e/e0e22218da9406ddc998de147bcda1f0-full", "genderGroup": "F", "previewUrlThumbSmall": "https://static-cdn.strpst.com/previews/e/6/4/e649a026d893e02017b7778e2015d9b2-thumb-small", "username": "-mi_mi-", "hlsPlaylist": "https://edge-hls.doppiocdn.com/hls/162696696/master/162696696_240p.m3u8", "snapshotServer": "eu5", "status": "public", "snapshotTimestamp": "1728899070", "broadcastSettings": {"width": 1920, "height": 1080}, "viewersCount": 41, "topBestPlace": 0, "publicRecordingsRate": 150, "privateRate": 60, "popularSnapshotTimestamp": 1728898650, "spyRate": 32, "p2pRate": 120, "p2pVoiceRate": 0, "id": 162696696, "hasGroupShowAnnouncement": false, "isNonNude": false, "isHd": true, "isVr": false, "isMobile": false, "isNew": false, "isLive": true, "isOnline": true, "isRecommended": false, "isTagVerified": false, "isModel": true, "isRotated": false, "isLovense": true, "isKiiroo": false, "doSpy": true, "doPrivate": true, "isAvatarApproved": true, "streamName": "162696696", "presets": ["720p", "480p", "240p", "160p", "160p_blurred"]}, {"gender": "female", "groupShowType": "", "groupShowTopic": "", "country": "", "broadcastGender": "female", "avatarUrl": "https://static-cdn.strpst.com/avatars/6/3/c/63c8120dbf9227f1b7b01a3b693259ce-full", "genderGroup": "F", "previewUrlThumbSmall": "https://static-cdn.strpst.com/previews/e/3/2/e325d43e4427223eb55c2f44d63d9d12-thumb-small", "username": "Mila825", "hlsPlaylist": "https://edge-hls.doppiocdn.com/hls/169125259/master/169125259.m3u8", "snapshotServer": "eu6", "status": "public", "snapshotTimestamp": "1728899070", "broadcastSettings": {"width": 864, "height": 480}, "viewersCount": 39, "topBestPlace": 0, "publicRecordingsRate": 8, "privateRate": 90, "popularSnapshotTimestamp": 1728898260, "spyRate": 60, "p2pRate": 120, "p2pVoiceRate": 0, "id": 169125259, "hasGroupShowAnnouncement": false, "isNonNude": false, "isHd": false, "isVr": false, "isMobile": false, "isNew": false, "isLive": true, "isOnline": true, "isRecommended": false, "isTagVerified": false, "isModel": true, "isRotated": false, "isLovense": false, "isKiiroo": false, "doSpy": true, "doPrivate": true, "isAvatarApproved": true, "streamName": "169125259", "presets": null}, {"gender": "female", "groupShowType": "", "groupShowTopic": "", "country": "", "broadcastGender": "female", "genderGroup": "F", "previewUrlThumbSmall": "https://static-cdn.strpst.com/previews/a/1/6/a165176ef7948b0303e014efaf46cb6d-thumb-small", "username": "tina0604", "hlsPlaylist": "https://edge-hls.doppiocdn.com/hls/123777793/master/123777793_240p.m3u8", "snapshotServer": "eu1", "status": "public", "snapshotTimestamp": "1728899070", "broadcastSettings": {"width": 1280, "height": 720}, "viewersCount": 39, "topBestPlace": 0, "publicRecordingsRate": 90, "privateRate": 44, "popularSnapshotTimestamp": 1728898320, "spyRate": 60, "p2pRate": 60, "p2pVoiceRate": 0, "id": 123777793, "hasGroupShowAnnouncement": false, "isNonNude": false, "isHd": true, "isVr": false, "isMobile": false, "isNew": false, "isLive": true, "isOnline": true, "isRecommended": false, "isTagVerified": false, "isModel": true, "isRotated": false, "isLovense": true, "isKiiroo": false, "doSpy": true, "doPrivate": true, "streamName": "123777793", "presets": ["720p", "480p", "240p", "160p", "160p_blurred"]}, {"gender": "female", "groupShowType": "", "groupShowTopic": "", "country": "cn", "broadcastGender": "female", "avatarUrl": "https://static-cdn.strpst.com/avatars/a/a/f/aafb7f5c38a23253f3df05bba095504a-full", "genderGroup": "F", "previewUrlThumbSmall": "https://static-cdn.strpst.com/previews/0/5/3/0537a34ac2da846c282a8e333541455f-thumb-small", "username": "Xiamo166", "hlsPlaylist": "https://edge-hls.doppiocdn.com/hls/151017094/master/151017094_1080p.m3u8", "snapshotServer": "eu6", "status": "public", "snapshotTimestamp": "1728899070", "broadcastSettings": {"width": 1920, "height": 1080}, "viewersCount": 37, "topBestPlace": 0, "publicRecordingsRate": 150, "privateRate": 60, "popularSnapshotTimestamp": 1728898500, "spyRate": 60, "p2pRate": 120, "p2pVoiceRate": 0, "id": 151017094, "hasGroupShowAnnouncement": false, "isNonNude": false, "isHd": true, "isVr": false, "isMobile": false, "isNew": false, "isLive": true, "isOnline": true, "isRecommended": false, "isTagVerified": false, "isModel": true, "isRotated": false, "isLovense": true, "isKiiroo": false, "doSpy": true, "doPrivate": true, "isAvatarApproved": true, "streamName": "151017094", "presets": ["1080p", "160p_blurred"]}, {"gender": "female", "groupShowType": "", "groupShowTopic": "", "country": "", "broadcastGender": "female", "avatarUrl": "https://static-cdn.strpst.com/avatars/c/f/5/cf573a7c00135fde1313c6a1c883cf47-full", "genderGroup": "F", "previewUrlThumbSmall": "https://static-cdn.strpst.com/previews/d/7/7/d7700d84ea5496f8b63f8847e473c722-thumb-small", "username": "Q-Babyy", "hlsPlaylist": "https://edge-hls.doppiocdn.com/hls/139432855/master/139432855.m3u8", "snapshotServer": "eu4", "status": "public", "snapshotTimestamp": "1728899070", "broadcastSettings": {"width": 508, "height": 678}, "viewersCount": 37, "topBestPlace": 0, "publicRecordingsRate": 150, "privateRate": 60, "popularSnapshotTimestamp": 1728898380, "spyRate": 44, "p2pRate": 90, "p2pVoiceRate": 0, "id": 139432855, "hasGroupShowAnnouncement": false, "isNonNude": false, "isHd": false, "isVr": false, "isMobile": true, "isNew": false, "isLive": true, "isOnline": true, "isRecommended": false, "isTagVerified": false, "isModel": true, "isRotated": false, "isLovense": true, "isKiiroo": false, "doSpy": true, "doPrivate": true, "isAvatarApproved": true, "streamName": "139432855", "presets": null}, {"gender": "female", "groupShowType": "", "groupShowTopic": "", "country": "", "broadcastGender": "female", "avatarUrl": "https://static-cdn.strpst.com/avatars/2/9/a/29a082f0beb1c8a3393d20de104ebfe4-full", "genderGroup": "F", "previewUrlThumbSmall": "https://static-cdn.strpst.com/previews/5/f/4/5f4e7a2ceb660aeae25dcf4646a2169c-thumb-small", "username": "Kuriki23", "hlsPlaylist": "https://edge-hls.doppiocdn.com/hls/157027036/master/157027036_240p.m3u8", "snapshotServer": "eu8", "status": "public", "snapshotTimestamp": "1728899070", "broadcastSettings": {"width": 1280, "height": 720}, "viewersCount": 34, "topBestPlace": 0, "publicRecordingsRate": 32, "privateRate": 44, "popularSnapshotTimestamp": 1728898560, "spyRate": 44, "p2pRate": 90, "p2pVoiceRate": 0, "id": 157027036, "hasGroupShowAnnouncement": false, "isNonNude": false, "isHd": true, "isVr": false, "isMobile": false, "isNew": false, "isLive": true, "isOnline": true, "isRecommended": false, "isTagVerified": false, "isModel": true, "isRotated": false, "isLovense": true, "isKiiroo": false, "doSpy": true, "doPrivate": true, "isAvatarApproved": true, "streamName": "157027036", "presets": ["720p", "480p", "240p", "160p", "160p_blurred"]}, {"gender": "female", "groupShowType": "", "groupShowTopic": "", "country": "", "broadcastGender": "female", "avatarUrl": "https://static-cdn.strpst.com/avatars/6/2/5/6257bfcc351c9bebea7c421220a5e975-full", "genderGroup": "F", "previewUrlThumbSmall": "https://static-cdn.strpst.com/previews/8/0/2/80208d9a54e85b5ffd395fbf67e56aab-thumb-small", "username": "Sweet-18wanwan", "hlsPlaylist": "https://edge-hls.doppiocdn.com/hls/113151028/master/113151028_240p.m3u8", "snapshotServer": "eu3", "status": "public", "snapshotTimestamp": "1728899070", "broadcastSettings": {"width": 1280, "height": 720}, "viewersCount": 32, "topBestPlace": 0, "publicRecordingsRate": 150, "privateRate": 60, "popularSnapshotTimestamp": 1728898230, "spyRate": 44, "p2pRate": 90, "p2pVoiceRate": 0, "id": 113151028, "hasGroupShowAnnouncement": false, "isNonNude": false, "isHd": true, "isVr": false, "isMobile": false, "isNew": false, "isLive": true, "isOnline": true, "isRecommended": false, "isTagVerified": false, "isModel": true, "isRotated": false, "isLovense": true, "isKiiroo": false, "doSpy": true, "doPrivate": true, "isAvatarApproved": true, "streamName": "113151028", "presets": ["720p", "480p", "240p", "160p", "160p_blurred"]}, {"gender": "female", "groupShowType": "", "groupShowTopic": "", "country": "cn", "broadcastGender": "female", "avatarUrl": "https://static-cdn.strpst.com/avatars/2/e/4/2e4a24189c6e0f1a90b3e8304b85b7b0-full", "genderGroup": "F", "previewUrlThumbSmall": "https://static-cdn.strpst.com/previews/1/b/2/1b2d0c713c28370c24915d1a1fdbe4d0-thumb-small", "username": "Hot-nini19", "hlsPlaylist": "https://edge-hls.doppiocdn.com/hls/110080458/master/110080458_240p.m3u8", "snapshotServer": "eu3", "status": "public", "snapshotTimestamp": "1728899070", "broadcastSettings": {"width": 1280, "height": 720}, "viewersCount": 31, "topBestPlace": 0, "publicRecordingsRate": 150, "privateRate": 90, "popularSnapshotTimestamp": 1728898200, "spyRate": 44, "p2pRate": 120, "p2pVoiceRate": 0, "id": 110080458, "hasGroupShowAnnouncement": false, "isNonNude": false, "isHd": true, "isVr": false, "isMobile": false, "isNew": false, "isLive": true, "isOnline": true, "isRecommended": false, "isTagVerified": false, "isModel": true, "isRotated": false, "isLovense": true, "isKiiroo": false, "doSpy": true, "doPrivate": true, "isAvatarApproved": true, "streamName": "110080458", "presets": ["480p", "240p", "160p", "160p_blurred"]}, {"gender": "female", "groupShowType": "", "groupShowTopic": "", "country": "", "broadcastGender": "female", "avatarUrl": "https://static-cdn.strpst.com/avatars/b/5/d/b5d4325d5d35daad6d2d23b34947f6fb-full", "genderGroup": "F", "previewUrlThumbSmall": "https://static-cdn.strpst.com/previews/f/5/9/f5947c2462ef0cc0785c3e62fe27fdc3-thumb-small", "username": "fafaai", "hlsPlaylist": "https://edge-hls.doppiocdn.com/hls/166481506/master/166481506_240p.m3u8", "snapshotServer": "eu11", "status": "public", "snapshotTimestamp": "1728899070", "broadcastSettings": {"width": 1920, "height": 1080}, "viewersCount": 31, "topBestPlace": 0, "publicRecordingsRate": 60, "privateRate": 60, "popularSnapshotTimestamp": 0, "spyRate": 44, "p2pRate": 90, "p2pVoiceRate": 0, "id": 166481506, "hasGroupShowAnnouncement": false, "isNonNude": false, "isHd": true, "isVr": false, "isMobile": false, "isNew": false, "isLive": true, "isOnline": true, "isRecommended": false, "isTagVerified": false, "isModel": true, "isRotated": false, "isLovense": true, "isKiiroo": false, "doSpy": true, "doPrivate": true, "isAvatarApproved": true, "streamName": "166481506", "presets": ["1080p60", "720p60", "720p", "480p", "240p", "160p", "160p_blurred"]}, {"gender": "female", "groupShowType": "", "groupShowTopic": "", "country": "", "broadcastGender": "female", "avatarUrl": "https://static-cdn.strpst.com/avatars/0/e/d/0eda0353360de23a912e0fc2ca4015ab-full", "genderGroup": "F", "previewUrlThumbSmall": "https://static-cdn.strpst.com/previews/d/4/e/d4e0c3ba8c3f95abf30a7fc27c806a61-thumb-small", "username": "Kulomiyee_koi", "hlsPlaylist": "https://edge-hls.doppiocdn.com/hls/172869227/master/172869227_240p.m3u8", "snapshotServer": "eu10", "status": "public", "snapshotTimestamp": "1728899070", "broadcastSettings": {"width": 1280, "height": 720}, "viewersCount": 31, "topBestPlace": 0, "publicRecordingsRate": 150, "privateRate": 90, "popularSnapshotTimestamp": 1728898260, "spyRate": 60, "p2pRate": 120, "p2pVoiceRate": 0, "id": 172869227, "hasGroupShowAnnouncement": false, "isNonNude": false, "isHd": true, "isVr": false, "isMobile": false, "isNew": true, "isLive": true, "isOnline": true, "isRecommended": false, "isTagVerified": false, "isModel": true, "isRotated": false, "isLovense": false, "isKiiroo": false, "doSpy": true, "doPrivate": true, "isAvatarApproved": true, "streamName": "172869227", "presets": ["720p", "480p", "240p", "160p", "160p_blurred"]}, {"gender": "female", "groupShowType": "", "groupShowTopic": "", "country": "", "broadcastGender": "female", "avatarUrl": "https://static-cdn.strpst.com/avatars/0/a/8/0a834ed6b696f44c03c12e2cfc28c6e3-full", "genderGroup": "F", "previewUrlThumbSmall": "https://static-cdn.strpst.com/previews/5/6/f/56f36b6d5ec905f906d20d2f23b5f845-thumb-small", "username": "y237", "hlsPlaylist": "https://edge-hls.doppiocdn.com/hls/173601759/master/173601759.m3u8", "snapshotServer": "eu8", "status": "public", "snapshotTimestamp": "1728899070", "broadcastSettings": {"width": 640, "height": 480}, "viewersCount": 31, "topBestPlace": 0, "publicRecordingsRate": 90, "privateRate": 90, "popularSnapshotTimestamp": 1728898620, "spyRate": 60, "p2pRate": 90, "p2pVoiceRate": 0, "id": 173601759, "hasGroupShowAnnouncement": false, "isNonNude": false, "isHd": false, "isVr": false, "isMobile": false, "isNew": true, "isLive": true, "isOnline": true, "isRecommended": false, "isTagVerified": false, "isModel": true, "isRotated": false, "isLovense": false, "isKiiroo": false, "doSpy": true, "doPrivate": true, "isAvatarApproved": true, "streamName": "173601759", "presets": null}, {"gender": "female", "groupShowType": "", "groupShowTopic": "", "country": "", "broadcastGender": "female", "avatarUrl": "https://static-cdn.strpst.com/avatars/b/8/f/b8f1b420291d9c227c19fc4102812f5e-full", "genderGroup": "F", "previewUrlThumbSmall": "https://static-cdn.strpst.com/previews/7/5/f/75f31b01c24ae4bed32449879ea866fe-thumb-small", "username": "BAISHI_KELE", "hlsPlaylist": "https://edge-hls.doppiocdn.com/hls/78137849/master/78137849_240p.m3u8", "snapshotServer": "eu11", "status": "public", "snapshotTimestamp": "1728899070", "broadcastSettings": {"width": 1280, "height": 720}, "viewersCount": 29, "topBestPlace": 0, "publicRecordingsRate": 8, "privateRate": 200, "popularSnapshotTimestamp": 1728898500, "spyRate": 60, "p2pRate": 200, "p2pVoiceRate": 0, "id": 78137849, "hasGroupShowAnnouncement": false, "isNonNude": false, "isHd": true, "isVr": false, "isMobile": false, "isNew": false, "isLive": true, "isOnline": true, "isRecommended": false, "isTagVerified": false, "isModel": true, "isRotated": false, "isLovense": false, "isKiiroo": false, "doSpy": true, "doPrivate": true, "isAvatarApproved": true, "streamName": "78137849", "presets": ["480p", "240p", "160p", "160p_blurred"]}, {"gender": "female", "groupShowType": "", "groupShowTopic": "", "country": "", "broadcastGender": "female", "avatarUrl": "https://static-cdn.strpst.com/avatars/1/e/9/1e92edcf964afa10d5ecf2785a237627-full", "genderGroup": "F", "previewUrlThumbSmall": "https://static-cdn.strpst.com/previews/6/9/0/6900ef5b54435472d07b255a475853a9-thumb-small", "username": "11-Q", "hlsPlaylist": "https://edge-hls.doppiocdn.com/hls/170779427/master/170779427_240p.m3u8", "snapshotServer": "eu12", "status": "public", "snapshotTimestamp": "1728899070", "broadcastSettings": {"width": 1280, "height": 720}, "viewersCount": 28, "topBestPlace": 0, "publicRecordingsRate": 150, "privateRate": 60, "popularSnapshotTimestamp": 1728898410, "spyRate": 60, "p2pRate": 90, "p2pVoiceRate": 0, "id": 170779427, "hasGroupShowAnnouncement": false, "isNonNude": false, "isHd": true, "isVr": false, "isMobile": false, "isNew": true, "isLive": true, "isOnline": true, "isRecommended": false, "isTagVerified": false, "isModel": true, "isRotated": false, "isLovense": true, "isKiiroo": false, "doSpy": true, "doPrivate": true, "isAvatarApproved": true, "streamName": "170779427", "presets": ["720p", "480p", "240p", "160p", "160p_blurred"]}, {"gender": "females", "groupShowType": "", "groupShowTopic": "", "country": "", "broadcastGender": "female", "avatarUrl": "https://static-cdn.strpst.com/avatars/0/7/4/074e2c6d3b2cfb3235718fa1e5884202-full", "genderGroup": "F", "previewUrlThumbSmall": "https://static-cdn.strpst.com/previews/3/7/0/3705145eeb6a2ba06bb69db9e89b8b05-thumb-small", "username": "SLG_sweetlolita_g1", "hlsPlaylist": "https://edge-hls.doppiocdn.com/hls/172393340/master/172393340_240p.m3u8", "snapshotServer": "eu10", "status": "public", "snapshotTimestamp": "1728899070", "broadcastSettings": {"width": 1920, "height": 1080}, "viewersCount": 27, "topBestPlace": 0, "publicRecordingsRate": 24, "privateRate": 0, "popularSnapshotTimestamp": 1728898500, "spyRate": 0, "p2pRate": 0, "p2pVoiceRate": 0, "id": 172393340, "hasGroupShowAnnouncement": false, "isNonNude": false, "isHd": true, "isVr": false, "isMobile": false, "isNew": true, "isLive": true, "isOnline": true, "isRecommended": false, "isTagVerified": false, "isModel": true, "isRotated": false, "isLovense": false, "isKiiroo": false, "doSpy": false, "doPrivate": false, "isAvatarApproved": true, "streamName": "172393340", "presets": ["1080p", "720p", "480p", "240p", "160p", "160p_blurred"]}, {"gender": "female", "groupShowType": "", "groupShowTopic": "", "country": "", "broadcastGender": "female", "avatarUrl": "https://static-cdn.strpst.com/avatars/b/a/0/ba070f457216cc17aec5ecef1367e706-full", "genderGroup": "F", "previewUrlThumbSmall": "https://static-cdn.strpst.com/previews/7/1/8/7181edbe8e1a347a1bfb88c5befb7729-thumb-small", "username": "LILYsweetfcup", "hlsPlaylist": "https://edge-hls.doppiocdn.com/hls/74875923/master/74875923_240p.m3u8", "snapshotServer": "eu6", "status": "public", "snapshotTimestamp": "1728899070", "broadcastSettings": {"width": 1280, "height": 720}, "viewersCount": 22, "topBestPlace": 0, "publicRecordingsRate": 24, "privateRate": 44, "popularSnapshotTimestamp": 1728898680, "spyRate": 16, "p2pRate": 60, "p2pVoiceRate": 0, "id": 74875923, "hasGroupShowAnnouncement": false, "isNonNude": false, "isHd": true, "isVr": false, "isMobile": false, "isNew": false, "isLive": true, "isOnline": true, "isRecommended": false, "isTagVerified": false, "isModel": true, "isRotated": false, "isLovense": true, "isKiiroo": false, "doSpy": true, "doPrivate": true, "isAvatarApproved": true, "streamName": "74875923", "presets": ["720p", "480p", "240p", "160p", "160p_blurred"]}, {"gender": "female", "groupShowType": "", "groupShowTopic": "", "country": "", "broadcastGender": "female", "avatarUrl": "https://static-cdn.strpst.com/avatars/8/0/3/80371d7a8c35862dcf25cf74d0f64534-full", "genderGroup": "F", "previewUrlThumbSmall": "https://static-cdn.strpst.com/previews/d/a/3/da3796de93f9f2cb14191403e846dc12-thumb-small", "username": "stripchat-yaoyao", "hlsPlaylist": "https://edge-hls.doppiocdn.com/hls/64423096/master/64423096_240p.m3u8", "snapshotServer": "eu8", "status": "public", "snapshotTimestamp": "1728899070", "broadcastSettings": {"width": 1920, "height": 1080}, "viewersCount": 19, "topBestPlace": 0, "publicRecordingsRate": 60, "privateRate": 44, "popularSnapshotTimestamp": 1728898500, "spyRate": 32, "p2pRate": 60, "p2pVoiceRate": 0, "id": 64423096, "hasGroupShowAnnouncement": false, "isNonNude": false, "isHd": true, "isVr": false, "isMobile": false, "isNew": false, "isLive": true, "isOnline": true, "isRecommended": false, "isTagVerified": false, "isModel": true, "isRotated": false, "isLovense": true, "isKiiroo": false, "doSpy": true, "doPrivate": true, "isAvatarApproved": true, "streamName": "64423096", "presets": ["1080p60", "720p60", "720p", "480p", "240p", "160p", "160p_blurred"]}, {"gender": "female", "groupShowType": "", "groupShowTopic": "", "country": "", "broadcastGender": "female", "genderGroup": "F", "previewUrlThumbSmall": "https://static-cdn.strpst.com/previews/8/f/0/8f04835d9c94146b808a3d8458c1b3f9-thumb-small", "username": "ccmmho1", "hlsPlaylist": "https://edge-hls.doppiocdn.com/hls/174456499/master/174456499.m3u8", "snapshotServer": "eu7", "status": "public", "snapshotTimestamp": "1728899070", "broadcastSettings": {"width": 864, "height": 480}, "viewersCount": 19, "topBestPlace": 0, "publicRecordingsRate": 150, "privateRate": 60, "popularSnapshotTimestamp": 1728898290, "spyRate": 60, "p2pRate": 90, "p2pVoiceRate": 0, "id": 174456499, "hasGroupShowAnnouncement": false, "isNonNude": false, "isHd": false, "isVr": false, "isMobile": false, "isNew": true, "isLive": true, "isOnline": true, "isRecommended": false, "isTagVerified": false, "isModel": true, "isRotated": false, "isLovense": false, "isKiiroo": false, "doSpy": true, "doPrivate": true, "streamName": "174456499", "presets": null}, {"gender": "female", "groupShowType": "", "groupShowTopic": "", "country": "", "broadcastGender": "female", "avatarUrl": "https://static-cdn.strpst.com/avatars/a/2/8/a2884a4b7351df9d5a16dd94ebfa81e4-full", "genderGroup": "F", "previewUrlThumbSmall": "https://static-cdn.strpst.com/previews/1/c/f/1cfee9b57c776f42dc141e8a6a292827-thumb-small", "username": "Aimee-520", "hlsPlaylist": "https://edge-hls.doppiocdn.com/hls/98008787/master/98008787_240p.m3u8", "snapshotServer": "eu6", "status": "public", "snapshotTimestamp": "1728899070", "broadcastSettings": {"width": 1920, "height": 1080}, "viewersCount": 18, "topBestPlace": 0, "publicRecordingsRate": 8, "privateRate": 90, "popularSnapshotTimestamp": 1728898260, "spyRate": 44, "p2pRate": 150, "p2pVoiceRate": 0, "id": 98008787, "hasGroupShowAnnouncement": false, "isNonNude": false, "isHd": true, "isVr": false, "isMobile": false, "isNew": false, "isLive": true, "isOnline": true, "isRecommended": false, "isTagVerified": false, "isModel": true, "isRotated": false, "isLovense": true, "isKiiroo": false, "doSpy": true, "doPrivate": true, "isAvatarApproved": true, "streamName": "98008787", "presets": ["1080p60", "720p60", "720p", "480p", "240p", "160p", "160p_blurred"]}, {"gender": "female", "groupShowType": "", "groupShowTopic": "", "country": "", "broadcastGender": "female", "avatarUrl": "https://static-cdn.strpst.com/avatars/4/a/9/4a9d261efa6facf6c2a9ebeb620de837-full", "genderGroup": "F", "previewUrlThumbSmall": "https://static-cdn.strpst.com/previews/6/c/5/6c5daafcf47fd03913cfb151422fd924-thumb-small", "username": "k0ra_", "hlsPlaylist": "https://edge-hls.doppiocdn.com/hls/166779387/master/166779387_240p.m3u8", "snapshotServer": "eu4", "status": "public", "snapshotTimestamp": "1728899070", "broadcastSettings": {"width": 1280, "height": 720}, "viewersCount": 17, "topBestPlace": 0, "publicRecordingsRate": 44, "privateRate": 44, "popularSnapshotTimestamp": 1728898710, "spyRate": 16, "p2pRate": 60, "p2pVoiceRate": 0, "id": 166779387, "hasGroupShowAnnouncement": false, "isNonNude": false, "isHd": true, "isVr": false, "isMobile": false, "isNew": false, "isLive": true, "isOnline": true, "isRecommended": false, "isTagVerified": false, "isModel": true, "isRotated": false, "isLovense": true, "isKiiroo": false, "doSpy": true, "doPrivate": true, "isAvatarApproved": true, "streamName": "166779387", "presets": ["720p", "480p", "240p", "160p", "160p_blurred"]}, {"gender": "female", "groupShowType": "", "groupShowTopic": "", "country": "", "broadcastGender": "female", "genderGroup": "F", "previewUrlThumbSmall": "https://static-cdn.strpst.com/previews/4/c/1/4c1a8f8e2de536d49fe51ffdf858985a-thumb-small", "username": "Uwuangie-", "hlsPlaylist": "https://edge-hls.doppiocdn.com/hls/173056290/master/173056290.m3u8", "snapshotServer": "eu1", "status": "public", "snapshotTimestamp": "1728899070", "broadcastSettings": {"width": 864, "height": 480}, "viewersCount": 17, "topBestPlace": 0, "publicRecordingsRate": 44, "privateRate": 24, "popularSnapshotTimestamp": 1728898770, "spyRate": 32, "p2pRate": 32, "p2pVoiceRate": 0, "id": 173056290, "hasGroupShowAnnouncement": false, "isNonNude": false, "isHd": false, "isVr": false, "isMobile": false, "isNew": true, "isLive": true, "isOnline": true, "isRecommended": false, "isTagVerified": false, "isModel": true, "isRotated": false, "isLovense": true, "isKiiroo": false, "doSpy": true, "doPrivate": true, "streamName": "173056290", "presets": null}, {"gender": "female", "groupShowType": "", "groupShowTopic": "", "country": "", "broadcastGender": "female", "avatarUrl": "https://static-cdn.strpst.com/avatars/c/1/f/c1f3336188cfddeaf53e0bedd62d13b2-full", "genderGroup": "F", "previewUrlThumbSmall": "https://static-cdn.strpst.com/previews/9/7/7/9772ce6759ec25d9db07bc0a96fc4381-thumb-small", "username": "Alien11223", "hlsPlaylist": "https://edge-hls.doppiocdn.com/hls/172415287/master/172415287_240p.m3u8", "snapshotServer": "eu1", "status": "public", "snapshotTimestamp": "1728899070", "broadcastSettings": {"width": 1280, "height": 720}, "viewersCount": 16, "topBestPlace": 0, "publicRecordingsRate": 150, "privateRate": 44, "popularSnapshotTimestamp": 1728898560, "spyRate": 44, "p2pRate": 60, "p2pVoiceRate": 0, "id": 172415287, "hasGroupShowAnnouncement": false, "isNonNude": false, "isHd": true, "isVr": false, "isMobile": false, "isNew": true, "isLive": true, "isOnline": true, "isRecommended": false, "isTagVerified": false, "isModel": true, "isRotated": false, "isLovense": false, "isKiiroo": false, "doSpy": true, "doPrivate": true, "isAvatarApproved": true, "streamName": "172415287", "presets": ["720p", "480p", "240p", "160p", "160p_blurred"]}, {"gender": "female", "groupShowType": "", "groupShowTopic": "", "country": "", "broadcastGender": "female", "avatarUrl": "https://static-cdn.strpst.com/avatars/1/5/9/1593e1bb07c1e71c26640347e7cccb64-full", "genderGroup": "F", "previewUrlThumbSmall": "https://static-cdn.strpst.com/previews/a/3/6/a360739a51af94f402521c5e330c5088-thumb-small", "username": "umi_cm", "hlsPlaylist": "https://edge-hls.doppiocdn.com/hls/164955630/master/164955630.m3u8", "snapshotServer": "eu5", "status": "public", "snapshotTimestamp": "1728899070", "broadcastSettings": {"width": 320, "height": 240}, "viewersCount": 16, "topBestPlace": 0, "publicRecordingsRate": 90, "privateRate": 60, "popularSnapshotTimestamp": 1728898950, "spyRate": 60, "p2pRate": 90, "p2pVoiceRate": 0, "id": 164955630, "hasGroupShowAnnouncement": false, "isNonNude": false, "isHd": false, "isVr": false, "isMobile": false, "isNew": true, "isLive": true, "isOnline": true, "isRecommended": false, "isTagVerified": false, "isModel": true, "isRotated": false, "isLovense": true, "isKiiroo": false, "doSpy": true, "doPrivate": true, "isAvatarApproved": true, "streamName": "164955630", "presets": null}, {"gender": "females", "groupShowType": "", "groupShowTopic": "", "country": "", "broadcastGender": "female", "genderGroup": "F", "previewUrlThumbSmall": "https://static-cdn.strpst.com/previews/7/b/9/7b9c264ec1db1c84f3b4112392805fe8-thumb-small", "username": "D18666", "hlsPlaylist": "https://edge-hls.doppiocdn.com/hls/173506739/master/173506739_480p.m3u8", "snapshotServer": "eu11", "status": "public", "snapshotTimestamp": "1728899070", "broadcastSettings": {"width": 864, "height": 480}, "viewersCount": 16, "topBestPlace": 0, "publicRecordingsRate": 8, "privateRate": 0, "popularSnapshotTimestamp": 1728898260, "spyRate": 0, "p2pRate": 0, "p2pVoiceRate": 0, "id": 173506739, "hasGroupShowAnnouncement": false, "isNonNude": false, "isHd": false, "isVr": false, "isMobile": false, "isNew": true, "isLive": true, "isOnline": false, "isRecommended": false, "isTagVerified": false, "isModel": true, "isRotated": false, "isLovense": false, "isKiiroo": false, "doSpy": false, "doPrivate": false, "streamName": "173506739", "presets": ["480p", "160p_blurred"]}, {"gender": "female", "groupShowType": "", "groupShowTopic": "", "country": "", "broadcastGender": "female", "avatarUrl": "https://static-cdn.strpst.com/avatars/a/d/b/adbfbd5d8d97d9c27a3d113164821e4a-full", "genderGroup": "F", "previewUrlThumbSmall": "https://static-cdn.strpst.com/previews/4/6/2/462455f3a4ceec67669910a3df842e51-thumb-small", "username": "babykitty-", "hlsPlaylist": "https://edge-hls.doppiocdn.com/hls/125533131/master/125533131_240p.m3u8", "snapshotServer": "eu12", "status": "public", "snapshotTimestamp": "1728899070", "broadcastSettings": {"width": 1280, "height": 720}, "viewersCount": 15, "topBestPlace": 0, "publicRecordingsRate": 60, "privateRate": 60, "popularSnapshotTimestamp": 1728898680, "spyRate": 60, "p2pRate": 200, "p2pVoiceRate": 0, "id": 125533131, "hasGroupShowAnnouncement": false, "isNonNude": false, "isHd": true, "isVr": false, "isMobile": false, "isNew": false, "isLive": true, "isOnline": true, "isRecommended": false, "isTagVerified": false, "isModel": true, "isRotated": false, "isLovense": false, "isKiiroo": false, "doSpy": true, "doPrivate": true, "isAvatarApproved": true, "streamName": "125533131", "presets": ["720p", "480p", "240p", "160p", "160p_blurred"]}, {"gender": "female", "groupShowType": "", "groupShowTopic": "", "country": "", "broadcastGender": "female", "avatarUrl": "https://static-cdn.strpst.com/avatars/7/3/7/7374f28914f3756d225a2d3e440fde40-full", "genderGroup": "F", "previewUrlThumbSmall": "https://static-cdn.strpst.com/previews/a/7/6/a765429a5f5485ba5db80c4763330bba-thumb-small", "username": "QQ88-99", "hlsPlaylist": "https://edge-hls.doppiocdn.com/hls/170274264/master/170274264_240p.m3u8", "snapshotServer": "eu4", "status": "public", "snapshotTimestamp": "1728899070", "broadcastSettings": {"width": 1920, "height": 1080}, "viewersCount": 14, "topBestPlace": 0, "publicRecordingsRate": 60, "privateRate": 90, "popularSnapshotTimestamp": 1728898890, "spyRate": 60, "p2pRate": 120, "p2pVoiceRate": 0, "id": 170274264, "hasGroupShowAnnouncement": false, "isNonNude": false, "isHd": true, "isVr": false, "isMobile": false, "isNew": false, "isLive": true, "isOnline": true, "isRecommended": false, "isTagVerified": false, "isModel": true, "isRotated": false, "isLovense": false, "isKiiroo": false, "doSpy": true, "doPrivate": true, "isAvatarApproved": true, "streamName": "170274264", "presets": ["1080p", "720p", "480p", "240p", "160p", "160p_blurred"]}, {"gender": "maleFemale", "groupShowType": "", "groupShowTopic": "", "country": "cn", "broadcastGender": "female", "avatarUrl": "https://static-cdn.strpst.com/avatars/d/1/3/d1344aa03160fff55ca910f5ce39c583-full", "genderGroup": "F", "previewUrlThumbSmall": "https://static-cdn.strpst.com/previews/6/7/9/67996b1fb6df90b97cb924491bac46b3-thumb-small", "username": "liu195874", "hlsPlaylist": "https://edge-hls.doppiocdn.com/hls/151542225/master/151542225.m3u8", "snapshotServer": "eu8", "status": "public", "snapshotTimestamp": "1728899070", "broadcastSettings": {"width": 640, "height": 480}, "viewersCount": 14, "topBestPlace": 0, "publicRecordingsRate": 120, "privateRate": 16, "popularSnapshotTimestamp": 1728898650, "spyRate": 16, "p2pRate": 24, "p2pVoiceRate": 0, "id": 151542225, "hasGroupShowAnnouncement": false, "isNonNude": false, "isHd": false, "isVr": false, "isMobile": false, "isNew": false, "isLive": true, "isOnline": true, "isRecommended": false, "isTagVerified": false, "isModel": true, "isRotated": false, "isLovense": false, "isKiiroo": false, "doSpy": true, "doPrivate": true, "isAvatarApproved": true, "streamName": "151542225", "presets": null}, {"gender": "female", "groupShowType": "", "groupShowTopic": "", "country": "", "broadcastGender": "female", "avatarUrl": "https://static-cdn.strpst.com/avatars/d/2/e/d2e4d8a9b04bc2e679807afa791a30c5-full", "genderGroup": "F", "previewUrlThumbSmall": "https://static-cdn.strpst.com/previews/7/8/4/7846064efef29765dd6a5e0ac9a3d2e9-thumb-small", "username": "-Frappuccino-", "hlsPlaylist": "https://edge-hls.doppiocdn.com/hls/167633262/master/167633262_240p.m3u8", "snapshotServer": "eu12", "status": "public", "snapshotTimestamp": "1728899070", "broadcastSettings": {"width": 1280, "height": 720}, "viewersCount": 13, "topBestPlace": 0, "publicRecordingsRate": 8, "privateRate": 200, "popularSnapshotTimestamp": 1728898560, "spyRate": 60, "p2pRate": 120, "p2pVoiceRate": 0, "id": 167633262, "hasGroupShowAnnouncement": false, "isNonNude": false, "isHd": true, "isVr": false, "isMobile": false, "isNew": false, "isLive": true, "isOnline": true, "isRecommended": false, "isTagVerified": false, "isModel": true, "isRotated": false, "isLovense": true, "isKiiroo": false, "doSpy": true, "doPrivate": true, "isAvatarApproved": true, "streamName": "167633262", "presets": ["720p", "480p", "240p", "160p", "160p_blurred"]}, {"gender": "females", "groupShowType": "", "groupShowTopic": "", "country": "", "broadcastGender": "female", "avatarUrl": "https://static-cdn.strpst.com/avatars/d/3/1/d31452c7425cfcbdd444cf2820c6c50f-full", "genderGroup": "F", "previewUrlThumbSmall": "https://static-cdn.strpst.com/previews/e/a/6/ea6cdb213feaf8953836adbce5d31fcc-thumb-small", "username": "CC__66", "hlsPlaylist": "https://edge-hls.doppiocdn.com/hls/146480163/master/146480163_240p.m3u8", "snapshotServer": "eu6", "status": "public", "snapshotTimestamp": "1728899070", "broadcastSettings": {"width": 1280, "height": 720}, "viewersCount": 9, "topBestPlace": 0, "publicRecordingsRate": 12, "privateRate": 60, "popularSnapshotTimestamp": 1728898320, "spyRate": 60, "p2pRate": 90, "p2pVoiceRate": 0, "id": 146480163, "hasGroupShowAnnouncement": false, "isNonNude": false, "isHd": true, "isVr": false, "isMobile": false, "isNew": false, "isLive": true, "isOnline": true, "isRecommended": false, "isTagVerified": false, "isModel": true, "isRotated": false, "isLovense": false, "isKiiroo": false, "doSpy": true, "doPrivate": true, "isAvatarApproved": true, "streamName": "146480163", "presets": ["720p", "480p", "240p", "160p", "160p_blurred"]}, {"gender": "female", "groupShowType": "", "groupShowTopic": "", "country": "", "broadcastGender": "female", "avatarUrl": "https://static-cdn.strpst.com/avatars/e/a/b/eab52dae05f89ef03f4725b905195da1-full", "genderGroup": "F", "previewUrlThumbSmall": "https://static-cdn.strpst.com/previews/5/6/2/562a417c53ef156063295e6e9216f12c-thumb-small", "username": "Susan-6", "hlsPlaylist": "https://edge-hls.doppiocdn.com/hls/173058605/master/173058605.m3u8", "snapshotServer": "eu1", "status": "public", "snapshotTimestamp": "1728899070", "broadcastSettings": {"width": 320, "height": 240}, "viewersCount": 8, "topBestPlace": 0, "publicRecordingsRate": 150, "privateRate": 32, "popularSnapshotTimestamp": 0, "spyRate": 24, "p2pRate": 44, "p2pVoiceRate": 0, "id": 173058605, "hasGroupShowAnnouncement": false, "isNonNude": false, "isHd": false, "isVr": false, "isMobile": false, "isNew": true, "isLive": true, "isOnline": true, "isRecommended": false, "isTagVerified": false, "isModel": true, "isRotated": false, "isLovense": true, "isKiiroo": false, "doSpy": true, "doPrivate": true, "isAvatarApproved": true, "streamName": "173058605", "presets": null}, {"gender": "female", "groupShowType": "", "groupShowTopic": "", "country": "", "broadcastGender": "female", "genderGroup": "F", "previewUrlThumbSmall": "https://static-cdn.strpst.com/previews/e/d/c/edc9a224ab8959f519028f24cacd04be-thumb-small", "username": "Sexy-hua", "hlsPlaylist": "https://edge-hls.doppiocdn.com/hls/172824017/master/172824017_1080p.m3u8", "snapshotServer": "eu11", "status": "public", "snapshotTimestamp": "1728899070", "broadcastSettings": {"width": 1920, "height": 1080}, "viewersCount": 8, "topBestPlace": 0, "publicRecordingsRate": 8, "privateRate": 44, "popularSnapshotTimestamp": 1728898410, "spyRate": 32, "p2pRate": 90, "p2pVoiceRate": 0, "id": 172824017, "hasGroupShowAnnouncement": false, "isNonNude": false, "isHd": true, "isVr": false, "isMobile": false, "isNew": true, "isLive": true, "isOnline": true, "isRecommended": false, "isTagVerified": false, "isModel": true, "isRotated": false, "isLovense": true, "isKiiroo": false, "doSpy": true, "doPrivate": true, "streamName": "172824017", "presets": ["1080p", "160p", "160p_blurred"]}, {"gender": "female", "groupShowType": "", "groupShowTopic": "", "country": "", "broadcastGender": "female", "avatarUrl": "https://static-cdn.strpst.com/avatars/1/c/d/1cd0ebdbb1c0800660eef3468bd6dbac-full", "genderGroup": "F", "previewUrlThumbSmall": "https://static-cdn.strpst.com/previews/c/8/2/c82af6bc1c0dbe5dfc5a1f5e201696c5-thumb-small", "username": "ZWYYKK", "hlsPlaylist": "https://edge-hls.doppiocdn.com/hls/171999978/master/171999978.m3u8", "snapshotServer": "eu1", "status": "public", "snapshotTimestamp": "1728899070", "broadcastSettings": {"width": 864, "height": 480}, "viewersCount": 8, "topBestPlace": 0, "publicRecordingsRate": 8, "privateRate": 0, "popularSnapshotTimestamp": 1728898620, "spyRate": 8, "p2pRate": 0, "p2pVoiceRate": 0, "id": 171999978, "hasGroupShowAnnouncement": false, "isNonNude": false, "isHd": false, "isVr": false, "isMobile": false, "isNew": true, "isLive": true, "isOnline": true, "isRecommended": false, "isTagVerified": false, "isModel": true, "isRotated": false, "isLovense": false, "isKiiroo": false, "doSpy": true, "doPrivate": false, "isAvatarApproved": true, "streamName": "171999978", "presets": null}, {"gender": "female", "groupShowType": "", "groupShowTopic": "", "country": "", "broadcastGender": "female", "genderGroup": "F", "previewUrlThumbSmall": "https://static-cdn.strpst.com/previews/f/1/e/f1edaa5045c9c107eafac0917614754e-thumb-small", "username": "Anine-888", "hlsPlaylist": "https://edge-hls.doppiocdn.com/hls/174581901/master/174581901_240p.m3u8", "snapshotServer": "eu10", "status": "public", "snapshotTimestamp": "1728899070", "broadcastSettings": {"width": 1280, "height": 720}, "viewersCount": 7, "topBestPlace": 0, "publicRecordingsRate": 8, "privateRate": 60, "popularSnapshotTimestamp": 1728898980, "spyRate": 16, "p2pRate": 90, "p2pVoiceRate": 0, "id": 174581901, "hasGroupShowAnnouncement": false, "isNonNude": false, "isHd": true, "isVr": false, "isMobile": false, "isNew": true, "isLive": true, "isOnline": true, "isRecommended": false, "isTagVerified": false, "isModel": true, "isRotated": false, "isLovense": true, "isKiiroo": false, "doSpy": true, "doPrivate": true, "streamName": "174581901", "presets": ["720p", "480p", "240p", "160p", "160p_blurred"]}, {"gender": "female", "groupShowType": "", "groupShowTopic": "", "country": "", "broadcastGender": "female", "avatarUrl": "https://static-cdn.strpst.com/avatars/8/e/3/8e3abeb69b1c693593fae1c4911459d9-full", "genderGroup": "F", "previewUrlThumbSmall": "https://static-cdn.strpst.com/previews/2/c/7/2c727996abfd7318f51884377f14ce77-thumb-small", "username": "-xiaoyu1314", "hlsPlaylist": "https://edge-hls.doppiocdn.com/hls/155429513/master/155429513_240p.m3u8", "snapshotServer": "eu7", "status": "public", "snapshotTimestamp": "1728899070", "broadcastSettings": {"width": 1280, "height": 720}, "viewersCount": 6, "topBestPlace": 0, "publicRecordingsRate": 8, "privateRate": 60, "popularSnapshotTimestamp": 1728898290, "spyRate": 12, "p2pRate": 90, "p2pVoiceRate": 0, "id": 155429513, "hasGroupShowAnnouncement": false, "isNonNude": false, "isHd": true, "isVr": false, "isMobile": false, "isNew": false, "isLive": true, "isOnline": true, "isRecommended": false, "isTagVerified": false, "isModel": true, "isRotated": false, "isLovense": true, "isKiiroo": false, "doSpy": true, "doPrivate": true, "isAvatarApproved": true, "streamName": "155429513", "presets": ["720p", "480p", "240p", "160p", "160p_blurred"]}, {"gender": "female", "groupShowType": "", "groupShowTopic": "", "country": "", "broadcastGender": "female", "avatarUrl": "https://static-cdn.strpst.com/avatars/8/f/a/8fa727d00802d0d0216a87e13cc431d9-full", "genderGroup": "F", "previewUrlThumbSmall": "https://static-cdn.strpst.com/previews/e/3/0/e30244506cce51b7d84627970430da5b-thumb-small", "username": "yiyi-1688", "hlsPlaylist": "https://edge-hls.doppiocdn.com/hls/172513613/master/172513613.m3u8", "snapshotServer": "eu4", "status": "public", "snapshotTimestamp": "1728899070", "broadcastSettings": {"width": 320, "height": 240}, "viewersCount": 6, "topBestPlace": 0, "publicRecordingsRate": 8, "privateRate": 60, "popularSnapshotTimestamp": 1728898500, "spyRate": 60, "p2pRate": 90, "p2pVoiceRate": 0, "id": 172513613, "hasGroupShowAnnouncement": false, "isNonNude": false, "isHd": false, "isVr": false, "isMobile": false, "isNew": true, "isLive": true, "isOnline": true, "isRecommended": false, "isTagVerified": false, "isModel": true, "isRotated": false, "isLovense": false, "isKiiroo": false, "doSpy": true, "doPrivate": true, "isAvatarApproved": true, "streamName": "172513613", "presets": null}, {"gender": "female", "groupShowType": "", "groupShowTopic": "", "country": "cn", "broadcastGender": "female", "avatarUrl": "https://static-cdn.strpst.com/avatars/f/c/3/fc311fdd049bce0e812f03c60f646f91-full", "genderGroup": "F", "previewUrlThumbSmall": "https://static-cdn.strpst.com/previews/a/3/9/a3905ece5e9e95fb12f8f4a734e85f76-thumb-small", "username": "-Shirleyni_", "hlsPlaylist": "https://edge-hls.doppiocdn.com/hls/111869229/master/111869229_240p.m3u8", "snapshotServer": "eu11", "status": "public", "snapshotTimestamp": "1728899070", "broadcastSettings": {"width": 1280, "height": 720}, "viewersCount": 5, "topBestPlace": 0, "publicRecordingsRate": 120, "privateRate": 32, "popularSnapshotTimestamp": 1728898500, "spyRate": 32, "p2pRate": 44, "p2pVoiceRate": 0, "id": 111869229, "hasGroupShowAnnouncement": false, "isNonNude": false, "isHd": true, "isVr": false, "isMobile": false, "isNew": false, "isLive": true, "isOnline": true, "isRecommended": false, "isTagVerified": false, "isModel": true, "isRotated": false, "isLovense": true, "isKiiroo": false, "doSpy": true, "doPrivate": true, "isAvatarApproved": true, "streamName": "111869229", "presets": ["480p", "240p", "160p", "160p_blurred"]}, {"gender": "female", "groupShowType": "", "groupShowTopic": "", "country": "", "broadcastGender": "female", "avatarUrl": "https://static-cdn.strpst.com/avatars/c/7/6/c76b9a59baf0eb68e97dea0e9d35ebc7-full", "genderGroup": "F", "previewUrlThumbSmall": "https://static-cdn.strpst.com/previews/a/e/7/ae7e2af47190aa9c7cb8f80ec5b2b256-thumb-small", "username": "kya66600", "hlsPlaylist": "https://edge-hls.doppiocdn.com/hls/168997364/master/168997364_240p.m3u8", "snapshotServer": "eu8", "status": "public", "snapshotTimestamp": "1728899070", "broadcastSettings": {"width": 1280, "height": 720}, "viewersCount": 5, "topBestPlace": 0, "publicRecordingsRate": 8, "privateRate": 60, "popularSnapshotTimestamp": 1728898350, "spyRate": 60, "p2pRate": 90, "p2pVoiceRate": 0, "id": 168997364, "hasGroupShowAnnouncement": false, "isNonNude": false, "isHd": true, "isVr": false, "isMobile": false, "isNew": false, "isLive": true, "isOnline": true, "isRecommended": false, "isTagVerified": false, "isModel": true, "isRotated": false, "isLovense": true, "isKiiroo": false, "doSpy": true, "doPrivate": true, "isAvatarApproved": true, "streamName": "168997364", "presets": ["240p", "160p", "160p_blurred"]}, {"gender": "female", "groupShowType": "", "groupShowTopic": "", "country": "", "broadcastGender": "female", "genderGroup": "F", "previewUrlThumbSmall": "https://static-cdn.strpst.com/previews/e/3/0/e3008f59234437086a5793f4f04daae3-thumb-small", "username": "nana-9527", "hlsPlaylist": "https://edge-hls.doppiocdn.com/hls/168560589/master/168560589_240p.m3u8", "snapshotServer": "eu2", "status": "public", "snapshotTimestamp": "1728899070", "broadcastSettings": {"width": 1280, "height": 720}, "viewersCount": 4, "topBestPlace": 0, "publicRecordingsRate": 8, "privateRate": 60, "popularSnapshotTimestamp": 1728898380, "spyRate": 60, "p2pRate": 90, "p2pVoiceRate": 0, "id": 168560589, "hasGroupShowAnnouncement": false, "isNonNude": false, "isHd": true, "isVr": false, "isMobile": false, "isNew": false, "isLive": true, "isOnline": true, "isRecommended": false, "isTagVerified": false, "isModel": true, "isRotated": false, "isLovense": false, "isKiiroo": false, "doSpy": true, "doPrivate": true, "streamName": "168560589", "presets": ["480p", "240p", "160p", "160p_blurred"]}, {"gender": "female", "groupShowType": "", "groupShowTopic": "", "country": "", "broadcastGender": "female", "avatarUrl": "https://static-cdn.strpst.com/avatars/0/f/4/0f483fd19c3bc39f084c3e2b7d585536-full", "genderGroup": "F", "previewUrlThumbSmall": "https://static-cdn.strpst.com/previews/1/e/5/1e56e60334553cb90ac6e53ac3239bf0-thumb-small", "username": "Elvira_baby", "hlsPlaylist": "https://edge-hls.doppiocdn.com/hls/94535827/master/94535827_240p.m3u8", "snapshotServer": "eu3", "status": "public", "snapshotTimestamp": "1728899070", "broadcastSettings": {"width": 1280, "height": 720}, "viewersCount": 3, "topBestPlace": 0, "publicRecordingsRate": 8, "privateRate": 32, "popularSnapshotTimestamp": 1728898650, "spyRate": 32, "p2pRate": 44, "p2pVoiceRate": 0, "id": 94535827, "hasGroupShowAnnouncement": false, "isNonNude": false, "isHd": true, "isVr": false, "isMobile": false, "isNew": false, "isLive": true, "isOnline": true, "isRecommended": false, "isTagVerified": false, "isModel": true, "isRotated": false, "isLovense": true, "isKiiroo": false, "doSpy": true, "doPrivate": true, "isAvatarApproved": true, "streamName": "94535827", "presets": ["720p", "480p", "240p", "160p", "160p_blurred"]}, {"gender": "female", "groupShowType": "", "groupShowTopic": "", "country": "", "broadcastGender": "female", "avatarUrl": "https://static-cdn.strpst.com/avatars/0/a/e/0ae588e1f7dbf89a02f4b7cc0f65f809-full", "genderGroup": "F", "previewUrlThumbSmall": "https://static-cdn.strpst.com/previews/d/e/1/de16020eb8864c4c4f3662eaecfc7641-thumb-small", "username": "Stylec66", "hlsPlaylist": "https://edge-hls.doppiocdn.com/hls/161409742/master/161409742_240p.m3u8", "snapshotServer": "eu2", "status": "public", "snapshotTimestamp": "1728899070", "broadcastSettings": {"width": 1280, "height": 720}, "viewersCount": 3, "topBestPlace": 0, "publicRecordingsRate": 8, "privateRate": 16, "popularSnapshotTimestamp": 1728898950, "spyRate": 32, "p2pRate": 32, "p2pVoiceRate": 0, "id": 161409742, "hasGroupShowAnnouncement": false, "isNonNude": false, "isHd": true, "isVr": false, "isMobile": false, "isNew": false, "isLive": true, "isOnline": true, "isRecommended": false, "isTagVerified": false, "isModel": true, "isRotated": false, "isLovense": true, "isKiiroo": false, "doSpy": true, "doPrivate": true, "isAvatarApproved": true, "streamName": "161409742", "presets": ["720p", "480p", "240p", "160p", "160p_blurred"]}, {"gender": "female", "groupShowType": "perMinute", "groupShowTopic": "\u8131\u8863\u821e", "country": "", "broadcastGender": "female", "genderGroup": "F", "previewUrlThumbSmall": "https://static-cdn.strpst.com/previews/2/7/8/2789b254a2fc62ad0e2ca0dce36423c0-thumb-small", "username": "lilihensao", "hlsPlaylist": "https://edge-hls.doppiocdn.com/hls/174157428/master/174157428_240p.m3u8", "snapshotServer": "eu12", "status": "groupShow", "snapshotTimestamp": "1728899070", "broadcastSettings": {"width": 1920, "height": 1080}, "viewersCount": 3, "topBestPlace": 0, "publicRecordingsRate": 8, "privateRate": 24, "popularSnapshotTimestamp": 0, "spyRate": 8, "p2pRate": 32, "p2pVoiceRate": 0, "id": 174157428, "hasGroupShowAnnouncement": false, "isNonNude": false, "isHd": true, "isVr": false, "isMobile": false, "isNew": true, "isLive": true, "isOnline": true, "isRecommended": false, "isTagVerified": false, "isModel": true, "isRotated": false, "isLovense": false, "isKiiroo": false, "doSpy": true, "doPrivate": true, "streamName": "174157428", "presets": ["1080p", "720p", "480p", "240p", "160p", "160p_blurred"]}, {"gender": "female", "groupShowType": "", "groupShowTopic": "", "country": "", "broadcastGender": "female", "avatarUrl": "https://static-cdn.strpst.com/avatars/d/7/e/d7effc68074c4f39ee66fb3f5b8649e5-full", "genderGroup": "F", "previewUrlThumbSmall": "https://static-cdn.strpst.com/previews/4/d/9/4d9eaeffa75d2fbb56aaaaf79b679873-thumb-small", "username": "tiantian314", "hlsPlaylist": "https://edge-hls.doppiocdn.com/hls/171954977/master/171954977_240p.m3u8", "snapshotServer": "eu10", "status": "public", "snapshotTimestamp": "1728899070", "broadcastSettings": {"width": 1280, "height": 720}, "viewersCount": 2, "topBestPlace": 0, "publicRecordingsRate": 8, "privateRate": 60, "popularSnapshotTimestamp": 1728898950, "spyRate": 60, "p2pRate": 150, "p2pVoiceRate": 0, "id": 171954977, "hasGroupShowAnnouncement": false, "isNonNude": false, "isHd": true, "isVr": false, "isMobile": false, "isNew": false, "isLive": true, "isOnline": true, "isRecommended": false, "isTagVerified": false, "isModel": true, "isRotated": false, "isLovense": false, "isKiiroo": false, "doSpy": true, "doPrivate": true, "isAvatarApproved": true, "streamName": "171954977", "presets": ["480p", "240p", "160p", "160p_blurred"]}, {"gender": "female", "groupShowType": "", "groupShowTopic": "", "country": "", "broadcastGender": "female", "genderGroup": "F", "previewUrlThumbSmall": "https://static-cdn.strpst.com/previews/7/d/9/7d9e400b65d84bc323fd7781667d917d-thumb-small", "username": "BeautifulGirl99", "hlsPlaylist": "https://edge-hls.doppiocdn.com/hls/173416975/master/173416975_240p.m3u8", "snapshotServer": "eu1", "status": "public", "snapshotTimestamp": "1728899070", "broadcastSettings": {"width": 1920, "height": 1080}, "viewersCount": 2, "topBestPlace": 0, "publicRecordingsRate": 8, "privateRate": 60, "popularSnapshotTimestamp": 1728898230, "spyRate": 8, "p2pRate": 90, "p2pVoiceRate": 0, "id": 173416975, "hasGroupShowAnnouncement": false, "isNonNude": false, "isHd": true, "isVr": false, "isMobile": false, "isNew": true, "isLive": true, "isOnline": true, "isRecommended": false, "isTagVerified": false, "isModel": true, "isRotated": false, "isLovense": false, "isKiiroo": false, "doSpy": true, "doPrivate": true, "streamName": "173416975", "presets": ["1080p", "720p", "480p", "240p", "160p", "160p_blurred"]}, {"gender": "female", "groupShowType": "", "groupShowTopic": "", "country": "", "broadcastGender": "female", "avatarUrl": "https://static-cdn.strpst.com/avatars/7/d/e/7deb385485d1db266f635f7e6eb91364-full", "genderGroup": "F", "previewUrlThumbSmall": "https://static-cdn.strpst.com/previews/5/f/6/5f61c7ae0b7b7d1f8e89188bdfc5e93c-thumb-small", "username": "wwcc123", "hlsPlaylist": "https://edge-hls.doppiocdn.com/hls/104320759/master/104320759.m3u8", "snapshotServer": "eu10", "status": "public", "snapshotTimestamp": "1728899070", "broadcastSettings": {"width": 864, "height": 480}, "viewersCount": 1, "topBestPlace": 0, "publicRecordingsRate": 8, "privateRate": 60, "popularSnapshotTimestamp": 1728898500, "spyRate": 60, "p2pRate": 90, "p2pVoiceRate": 0, "id": 104320759, "hasGroupShowAnnouncement": false, "isNonNude": false, "isHd": false, "isVr": false, "isMobile": false, "isNew": false, "isLive": true, "isOnline": true, "isRecommended": false, "isTagVerified": false, "isModel": true, "isRotated": false, "isLovense": false, "isKiiroo": false, "doSpy": true, "doPrivate": true, "isAvatarApproved": true, "streamName": "104320759", "presets": null}, {"gender": "female", "groupShowType": "perMinute", "groupShowTopic": "\u770b\u6211\u8089\u7a74", "country": "", "broadcastGender": "female", "genderGroup": "F", "previewUrlThumbSmall": "https://static-cdn.strpst.com/previews/3/a/3/3a38e17192cb2e929a439a6a559d4d9d-thumb-small", "username": "HOT7409", "hlsPlaylist": "https://edge-hls.doppiocdn.com/hls/173947470/master/173947470_240p.m3u8", "snapshotServer": "eu1", "status": "groupShow", "snapshotTimestamp": "1728899070", "broadcastSettings": {"width": 1920, "height": 1080}, "viewersCount": 1, "topBestPlace": 0, "publicRecordingsRate": 8, "privateRate": 24, "popularSnapshotTimestamp": 0, "spyRate": 8, "p2pRate": 32, "p2pVoiceRate": 0, "id": 173947470, "hasGroupShowAnnouncement": false, "isNonNude": false, "isHd": true, "isVr": false, "isMobile": false, "isNew": true, "isLive": true, "isOnline": true, "isRecommended": false, "isTagVerified": false, "isModel": true, "isRotated": false, "isLovense": false, "isKiiroo": false, "doSpy": true, "doPrivate": true, "streamName": "173947470", "presets": ["1080p", "720p", "480p", "240p", "160p", "160p_blurred"]}]