[{"gender": "female", "groupShowType": "", "country": "", "broadcastGender": "female", "avatarUrl": "https://static-cdn.strpst.com/avatars/b/d/9/bd9a3433b8913dcbfacefd4dfb81bb51-full", "genderGroup": "F", "previewUrlThumbBig": "https://static-cdn.strpst.com/previews/0/a/9/0a997f0dc1c901c9754a04bc4961a89b-thumb-big", "previewUrlThumbSmall": "https://static-cdn.strpst.com/previews/0/a/9/0a997f0dc1c901c9754a04bc4961a89b-thumb-small", "username": "MandyLovesYou", "hlsPlaylist": "https://edge-hls.doppiocdn.com/hls/121329835/master/121329835_240p.m3u8", "snapshotServer": "us25", "status": "public", "snapshotTimestamp": "1690570080", "broadcastSettings": {"width": 1280, "height": 720}, "viewersCount": 487, "topBestPlace": 0, "publicRecordingsRate": 90, "privateRate": 60, "popularSnapshotTimestamp": 0, "spyRate": 60, "p2pRate": 120, "p2pVoiceRate": 0, "id": 121329835, "hasGroupShowAnnouncement": false, "isNonNude": false, "isHd": true, "isVr": false, "isMobile": false, "isNew": true, "isLive": true, "isOnline": true, "isRecommended": false, "isTagVerified": false, "isModel": true, "isLovense": true, "isKiiroo": false, "doSpy": true, "doPrivate": true, "isAvatarApproved": true}, {"gender": "maleFemale", "groupShowType": "", "country": "", "broadcastGender": "group", "avatarUrl": "https://static-cdn.strpst.com/avatars/9/a/c/9ac0ef147fa8fa84c59bc2468c6de81f-full", "genderGroup": "F", "previewUrlThumbBig": "https://static-cdn.strpst.com/previews/3/6/f/36f7af3dd35c074e8616eea99c839f01-thumb-big", "previewUrlThumbSmall": "https://static-cdn.strpst.com/previews/3/6/f/36f7af3dd35c074e8616eea99c839f01-thumb-small", "username": "__Lab__", "hlsPlaylist": "https://edge-hls.doppiocdn.com/hls/117376122/master/117376122_240p.m3u8", "snapshotServer": "us25", "status": "public", "snapshotTimestamp": "1690570080", "broadcastSettings": {"width": 1920, "height": 1080}, "viewersCount": 705, "topBestPlace": 0, "publicRecordingsRate": 150, "privateRate": 200, "popularSnapshotTimestamp": 1690569510, "spyRate": 0, "p2pRate": 250, "p2pVoiceRate": 0, "id": 117376122, "hasGroupShowAnnouncement": false, "isNonNude": false, "isHd": true, "isVr": false, "isMobile": false, "isNew": false, "isLive": true, "isOnline": true, "isRecommended": false, "isTagVerified": false, "isModel": true, "isLovense": true, "isKiiroo": false, "doSpy": false, "doPrivate": true, "isAvatarApproved": true}, {"gender": "maleFemale", "groupShowType": "", "country": "ca", "broadcastGender": "female", "avatarUrl": "https://static-cdn.strpst.com/avatars/0/6/4/064dde0374fe82b95d2204f5eb11f65a-full", "genderGroup": "F", "previewUrlThumbBig": "https://static-cdn.strpst.com/previews/e/3/f/e3f37bf6328b02f517683f05fdff849c-thumb-big", "previewUrlThumbSmall": "https://static-cdn.strpst.com/previews/e/3/f/e3f37bf6328b02f517683f05fdff849c-thumb-small", "username": "BadAngels666", "hlsPlaylist": "https://edge-hls.doppiocdn.com/hls/72074659/master/72074659_240p.m3u8", "snapshotServer": "us25", "status": "public", "snapshotTimestamp": "1690570080", "broadcastSettings": {"width": 1920, "height": 1080}, "viewersCount": 463, "topBestPlace": 18, "publicRecordingsRate": 32, "privateRate": 60, "popularSnapshotTimestamp": 1690569210, "spyRate": 16, "p2pRate": 90, "p2pVoiceRate": 0, "id": 72074659, "hasGroupShowAnnouncement": false, "isNonNude": false, "isHd": true, "isVr": false, "isMobile": false, "isNew": false, "isLive": true, "isOnline": true, "isRecommended": false, "isTagVerified": false, "isModel": true, "isLovense": true, "isKiiroo": false, "doSpy": true, "doPrivate": true, "isAvatarApproved": true}, {"gender": "female", "groupShowType": "ticket", "country": "", "broadcastGender": "female", "avatarUrl": "https://static-cdn.strpst.com/avatars/b/7/e/b7e9b2ccedb2f5f1201144cb85500bc6-full", "genderGroup": "F", "previewUrlThumbBig": "https://static-cdn.strpst.com/previews/2/e/f/2efecd4ab87eb7f72a5b5aea27375dbc-thumb-big", "previewUrlThumbSmall": "https://static-cdn.strpst.com/previews/2/e/f/2efecd4ab87eb7f72a5b5aea27375dbc-thumb-small", "username": "Peggy--fun", "hlsPlaylist": "https://edge-hls.doppiocdn.com/hls/94620867/master/94620867_240p.m3u8", "snapshotServer": "us23", "status": "groupShow", "snapshotTimestamp": "1690570080", "broadcastSettings": {"width": 1280, "height": 720}, "viewersCount": 413, "topBestPlace": 1, "publicRecordingsRate": 60, "privateRate": 90, "popularSnapshotTimestamp": 1690569450, "spyRate": 60, "p2pRate": 150, "p2pVoiceRate": 0, "id": 94620867, "hasGroupShowAnnouncement": false, "isNonNude": false, "isHd": true, "isVr": false, "isMobile": false, "isNew": false, "isLive": true, "isOnline": true, "isRecommended": false, "isTagVerified": false, "isModel": true, "isLovense": false, "isKiiroo": false, "doSpy": true, "doPrivate": true, "isAvatarApproved": true}, {"gender": "female", "groupShowType": "", "country": "cn", "broadcastGender": "female", "avatarUrl": "https://static-cdn.strpst.com/avatars/9/c/2/9c272a47acae949f5db42c917a24e870-full", "genderGroup": "F", "previewUrlThumbBig": "https://static-cdn.strpst.com/previews/a/9/2/a92b22b08d9947ebbbf385a2cbfb426e-thumb-big", "previewUrlThumbSmall": "https://static-cdn.strpst.com/previews/a/9/2/a92b22b08d9947ebbbf385a2cbfb426e-thumb-small", "username": "JennyJoice", "hlsPlaylist": "https://edge-hls.doppiocdn.com/hls/86590299/master/86590299_240p.m3u8", "snapshotServer": "us22", "status": "public", "snapshotTimestamp": "1690570080", "broadcastSettings": {"width": 1280, "height": 720}, "viewersCount": 1293, "topBestPlace": 63, "publicRecordingsRate": 8, "privateRate": 60, "popularSnapshotTimestamp": 1690569900, "spyRate": 60, "p2pRate": 120, "p2pVoiceRate": 0, "id": 86590299, "hasGroupShowAnnouncement": false, "isNonNude": false, "isHd": true, "isVr": false, "isMobile": false, "isNew": false, "isLive": true, "isOnline": true, "isRecommended": false, "isTagVerified": false, "isModel": true, "isLovense": true, "isKiiroo": false, "doSpy": true, "doPrivate": true, "isAvatarApproved": true}, {"gender": "female", "groupShowType": "", "country": "", "broadcastGender": "female", "avatarUrl": "https://static-cdn.strpst.com/avatars/8/3/9/839321da25ec553c467c1e5bd60031e2-full", "genderGroup": "F", "previewUrlThumbBig": "https://static-cdn.strpst.com/previews/5/a/5/5a5920d42bbe1b7e63504dcef93e2583-thumb-big", "previewUrlThumbSmall": "https://static-cdn.strpst.com/previews/5/a/5/5a5920d42bbe1b7e63504dcef93e2583-thumb-small", "username": "610Stella", "hlsPlaylist": "https://edge-hls.doppiocdn.com/hls/63188730/master/63188730_240p.m3u8", "snapshotServer": "us22", "status": "public", "snapshotTimestamp": "1690570080", "broadcastSettings": {"width": 1920, "height": 1080}, "viewersCount": 629, "topBestPlace": 1, "publicRecordingsRate": 44, "privateRate": 90, "popularSnapshotTimestamp": 1690569180, "spyRate": 60, "p2pRate": 200, "p2pVoiceRate": 0, "id": 63188730, "hasGroupShowAnnouncement": false, "isNonNude": false, "isHd": true, "isVr": false, "isMobile": false, "isNew": false, "isLive": true, "isOnline": true, "isRecommended": false, "isTagVerified": false, "isModel": true, "isLovense": true, "isKiiroo": false, "doSpy": true, "doPrivate": true, "isAvatarApproved": true}, {"gender": "female", "groupShowType": "", "country": "cn", "broadcastGender": "female", "avatarUrl": "https://static-cdn.strpst.com/avatars/0/3/a/03a4bb5b7ea6a0384106965978560261-full", "genderGroup": "F", "previewUrlThumbBig": "https://static-cdn.strpst.com/previews/5/9/c/59cfd62f9ff7fd00bd58e6efaab9d0c8-thumb-big", "previewUrlThumbSmall": "https://static-cdn.strpst.com/previews/5/9/c/59cfd62f9ff7fd00bd58e6efaab9d0c8-thumb-small", "username": "hhkkuu123", "hlsPlaylist": "https://edge-hls.doppiocdn.com/hls/105412868/master/105412868_240p.m3u8", "snapshotServer": "us26", "status": "public", "snapshotTimestamp": "1690570080", "broadcastSettings": {"width": 1920, "height": 1080}, "viewersCount": 472, "topBestPlace": 26, "publicRecordingsRate": 150, "privateRate": 60, "popularSnapshotTimestamp": 1690569300, "spyRate": 60, "p2pRate": 120, "p2pVoiceRate": 0, "id": 105412868, "hasGroupShowAnnouncement": false, "isNonNude": false, "isHd": true, "isVr": false, "isMobile": false, "isNew": false, "isLive": true, "isOnline": true, "isRecommended": false, "isTagVerified": false, "isModel": true, "isLovense": true, "isKiiroo": false, "doSpy": true, "doPrivate": true, "isAvatarApproved": true}, {"gender": "female", "groupShowType": "", "country": "", "broadcastGender": "female", "avatarUrl": "https://static-cdn.strpst.com/avatars/6/d/3/6d31f866bbbf046e1bf5d0be906ab970-full", "genderGroup": "F", "previewUrlThumbBig": "https://static-cdn.strpst.com/previews/b/1/c/b1c884a0611c375cd6b82d0db4ca9125-thumb-big", "previewUrlThumbSmall": "https://static-cdn.strpst.com/previews/b/1/c/b1c884a0611c375cd6b82d0db4ca9125-thumb-small", "username": "Sa_shimi", "hlsPlaylist": "https://edge-hls.doppiocdn.com/hls/36433974/master/36433974_240p.m3u8", "snapshotServer": "", "status": "idle", "snapshotTimestamp": "1690570080", "broadcastSettings": {"width": 1920, "height": 1080}, "viewersCount": 120, "topBestPlace": 42, "publicRecordingsRate": 150, "privateRate": 120, "popularSnapshotTimestamp": 1690569690, "spyRate": 60, "p2pRate": 150, "p2pVoiceRate": 0, "id": 36433974, "hasGroupShowAnnouncement": false, "isNonNude": false, "isHd": true, "isVr": false, "isMobile": false, "isNew": false, "isLive": false, "isOnline": true, "isRecommended": false, "isTagVerified": false, "isModel": true, "isLovense": false, "isKiiroo": false, "doSpy": true, "doPrivate": true, "isAvatarApproved": true}, {"gender": "female", "groupShowType": "", "country": "", "broadcastGender": "female", "avatarUrl": "https://static-cdn.strpst.com/avatars/0/9/9/099d8fb01bd62a97fa6da09c1792f3f1-full", "genderGroup": "F", "previewUrlThumbBig": "https://static-cdn.strpst.com/previews/2/0/c/20ca98c867703e64bd1ffadf67f48100-thumb-big", "previewUrlThumbSmall": "https://static-cdn.strpst.com/previews/2/0/c/20ca98c867703e64bd1ffadf67f48100-thumb-small", "username": "Doll-bb", "hlsPlaylist": "https://edge-hls.doppiocdn.com/hls/118832298/master/118832298_240p.m3u8", "snapshotServer": "us22", "status": "public", "snapshotTimestamp": "1690570080", "broadcastSettings": {"width": 1920, "height": 1080}, "viewersCount": 319, "topBestPlace": 0, "publicRecordingsRate": 150, "privateRate": 120, "popularSnapshotTimestamp": 1690569570, "spyRate": 60, "p2pRate": 200, "p2pVoiceRate": 0, "id": 118832298, "hasGroupShowAnnouncement": false, "isNonNude": false, "isHd": true, "isVr": false, "isMobile": false, "isNew": false, "isLive": true, "isOnline": true, "isRecommended": false, "isTagVerified": false, "isModel": true, "isLovense": false, "isKiiroo": false, "doSpy": true, "doPrivate": true, "isAvatarApproved": true}, {"gender": "female", "groupShowType": "", "country": "", "broadcastGender": "female", "avatarUrl": "https://static-cdn.strpst.com/avatars/a/e/c/aecc34454736abe17c18a0550f35b997-full", "genderGroup": "F", "previewUrlThumbBig": "https://static-cdn.strpst.com/previews/a/9/6/a966d09344f667134e0b47910d3b0da8-thumb-big", "previewUrlThumbSmall": "https://static-cdn.strpst.com/previews/a/9/6/a966d09344f667134e0b47910d3b0da8-thumb-small", "username": "BabyXiaoQi", "hlsPlaylist": "https://edge-hls.doppiocdn.com/hls/119566710/master/119566710_240p.m3u8", "snapshotServer": "us22", "status": "public", "snapshotTimestamp": "1690570080", "broadcastSettings": {"width": 1280, "height": 720}, "viewersCount": 96, "topBestPlace": 0, "publicRecordingsRate": 120, "privateRate": 60, "popularSnapshotTimestamp": 1690569420, "spyRate": 60, "p2pRate": 120, "p2pVoiceRate": 0, "id": 119566710, "hasGroupShowAnnouncement": false, "isNonNude": false, "isHd": true, "isVr": false, "isMobile": false, "isNew": false, "isLive": true, "isOnline": true, "isRecommended": false, "isTagVerified": false, "isModel": true, "isLovense": true, "isKiiroo": false, "doSpy": true, "doPrivate": true, "isAvatarApproved": true}, {"gender": "female", "groupShowType": "", "country": "", "broadcastGender": "female", "avatarUrl": "https://static-cdn.strpst.com/avatars/1/b/0/1b043464da3a606b99c55df1b4751540-full", "genderGroup": "F", "previewUrlThumbBig": "https://static-cdn.strpst.com/previews/0/a/9/0a932b22065fd5f409c9cf279925796a-thumb-big", "previewUrlThumbSmall": "https://static-cdn.strpst.com/previews/0/a/9/0a932b22065fd5f409c9cf279925796a-thumb-small", "username": "Happy-bibi", "hlsPlaylist": "https://edge-hls.doppiocdn.com/hls/121071547/master/121071547_240p.m3u8", "snapshotServer": "us23", "status": "public", "snapshotTimestamp": "1690570080", "broadcastSettings": {"width": 1280, "height": 720}, "viewersCount": 312, "topBestPlace": 0, "publicRecordingsRate": 8, "privateRate": 44, "popularSnapshotTimestamp": 1690569540, "spyRate": 60, "p2pRate": 60, "p2pVoiceRate": 0, "id": 121071547, "hasGroupShowAnnouncement": false, "isNonNude": false, "isHd": true, "isVr": false, "isMobile": false, "isNew": true, "isLive": true, "isOnline": true, "isRecommended": false, "isTagVerified": false, "isModel": true, "isLovense": true, "isKiiroo": false, "doSpy": true, "doPrivate": true, "isAvatarApproved": true}, {"gender": "female", "groupShowType": "", "country": "", "broadcastGender": "female", "avatarUrl": "https://static-cdn.strpst.com/avatars/3/a/d/3ad64394a60ff8809023838344e9df07-full", "genderGroup": "F", "previewUrlThumbBig": "https://static-cdn.strpst.com/previews/2/f/a/2fac32aa5bfe6d9cde9da7f3fac7fb94-thumb-big", "previewUrlThumbSmall": "https://static-cdn.strpst.com/previews/2/f/a/2fac32aa5bfe6d9cde9da7f3fac7fb94-thumb-small", "username": "jiayin-520", "hlsPlaylist": "https://edge-hls.doppiocdn.com/hls/119654011/master/119654011_240p.m3u8", "snapshotServer": "us24", "status": "public", "snapshotTimestamp": "1690570080", "broadcastSettings": {"width": 1920, "height": 1080}, "viewersCount": 283, "topBestPlace": 0, "publicRecordingsRate": 150, "privateRate": 0, "popularSnapshotTimestamp": 1690569630, "spyRate": 0, "p2pRate": 90, "p2pVoiceRate": 0, "id": 119654011, "hasGroupShowAnnouncement": false, "isNonNude": false, "isHd": true, "isVr": false, "isMobile": false, "isNew": false, "isLive": true, "isOnline": true, "isRecommended": false, "isTagVerified": false, "isModel": true, "isLovense": true, "isKiiroo": false, "doSpy": false, "doPrivate": false, "isAvatarApproved": true}, {"gender": "female", "groupShowType": "", "country": "", "broadcastGender": "female", "avatarUrl": "https://static-cdn.strpst.com/avatars/f/0/d/f0d4e539e63524f6e4dffc9a3bc0073a-full", "genderGroup": "F", "previewUrlThumbBig": "https://static-cdn.strpst.com/previews/8/6/6/86605125b4d291f6b6f15027a98940e7-thumb-big", "previewUrlThumbSmall": "https://static-cdn.strpst.com/previews/8/6/6/86605125b4d291f6b6f15027a98940e7-thumb-small", "username": "Ms_beautiful", "hlsPlaylist": "https://edge-hls.doppiocdn.com/hls/96348688/master/96348688_240p.m3u8", "snapshotServer": "us23", "status": "public", "snapshotTimestamp": "1690570080", "broadcastSettings": {"width": 1280, "height": 720}, "viewersCount": 198, "topBestPlace": 10, "publicRecordingsRate": 120, "privateRate": 120, "popularSnapshotTimestamp": 1690569390, "spyRate": 60, "p2pRate": 150, "p2pVoiceRate": 0, "id": 96348688, "hasGroupShowAnnouncement": false, "isNonNude": false, "isHd": true, "isVr": false, "isMobile": false, "isNew": false, "isLive": true, "isOnline": true, "isRecommended": false, "isTagVerified": false, "isModel": true, "isLovense": true, "isKiiroo": false, "doSpy": true, "doPrivate": true, "isAvatarApproved": true}, {"gender": "female", "groupShowType": "", "country": "cn", "broadcastGender": "female", "avatarUrl": "https://static-cdn.strpst.com/avatars/1/f/3/1f3b5742c1ec62ea94372c8cbb4516a8-full", "genderGroup": "F", "previewUrlThumbBig": "https://static-cdn.strpst.com/previews/d/6/d/d6d73d7f0c77d0304a71d7eaf25fccc7-thumb-big", "previewUrlThumbSmall": "https://static-cdn.strpst.com/previews/d/6/d/d6d73d7f0c77d0304a71d7eaf25fccc7-thumb-small", "username": "nefelibata-00", "hlsPlaylist": "https://edge-hls.doppiocdn.com/hls/80790540/master/80790540_240p.m3u8", "snapshotServer": "us26", "status": "public", "snapshotTimestamp": "1690570080", "broadcastSettings": {"width": 1280, "height": 720}, "viewersCount": 305, "topBestPlace": 54, "publicRecordingsRate": 150, "privateRate": 90, "popularSnapshotTimestamp": 1690569660, "spyRate": 60, "p2pRate": 120, "p2pVoiceRate": 0, "id": 80790540, "hasGroupShowAnnouncement": false, "isNonNude": false, "isHd": true, "isVr": false, "isMobile": false, "isNew": false, "isLive": true, "isOnline": true, "isRecommended": false, "isTagVerified": false, "isModel": true, "isLovense": false, "isKiiroo": false, "doSpy": true, "doPrivate": true, "isAvatarApproved": true}, {"gender": "female", "groupShowType": "", "country": "tw", "broadcastGender": "female", "avatarUrl": "https://static-cdn.strpst.com/avatars/c/8/1/c812e8188c110462828dfef3f2185b2d-full", "genderGroup": "F", "previewUrlThumbBig": "https://static-cdn.strpst.com/previews/0/3/f/03f910045fb8a6b9b653f54451410028-thumb-big", "previewUrlThumbSmall": "https://static-cdn.strpst.com/previews/0/3/f/03f910045fb8a6b9b653f54451410028-thumb-small", "username": "tw_love", "hlsPlaylist": "https://edge-hls.doppiocdn.com/hls/56837042/master/56837042_240p.m3u8", "snapshotServer": "us26", "status": "public", "snapshotTimestamp": "1690570080", "broadcastSettings": {"width": 1280, "height": 720}, "viewersCount": 53, "topBestPlace": 0, "publicRecordingsRate": 8, "privateRate": 60, "popularSnapshotTimestamp": 1690569300, "spyRate": 60, "p2pRate": 90, "p2pVoiceRate": 0, "id": 56837042, "hasGroupShowAnnouncement": false, "isNonNude": false, "isHd": true, "isVr": false, "isMobile": false, "isNew": false, "isLive": true, "isOnline": true, "isRecommended": false, "isTagVerified": false, "isModel": true, "isLovense": true, "isKiiroo": false, "doSpy": true, "doPrivate": true, "isAvatarApproved": true}, {"gender": "female", "groupShowType": "", "country": "", "broadcastGender": "female", "avatarUrl": "https://static-cdn.strpst.com/avatars/3/8/c/38ce8290660abc6de2db18b497124f4d-full", "genderGroup": "F", "previewUrlThumbBig": "https://static-cdn.strpst.com/previews/b/7/f/b7fe463ee77b1fc463d491f9ddaed8ee-thumb-big", "previewUrlThumbSmall": "https://static-cdn.strpst.com/previews/b/7/f/b7fe463ee77b1fc463d491f9ddaed8ee-thumb-small", "username": "Eup_Mona", "hlsPlaylist": "https://edge-hls.doppiocdn.com/hls/105515374/master/105515374_240p.m3u8", "snapshotServer": "us24", "status": "public", "snapshotTimestamp": "1690570080", "broadcastSettings": {"width": 1280, "height": 720}, "viewersCount": 349, "topBestPlace": 32, "publicRecordingsRate": 8, "privateRate": 44, "popularSnapshotTimestamp": 0, "spyRate": 60, "p2pRate": 120, "p2pVoiceRate": 0, "id": 105515374, "hasGroupShowAnnouncement": false, "isNonNude": false, "isHd": true, "isVr": false, "isMobile": false, "isNew": false, "isLive": true, "isOnline": true, "isRecommended": false, "isTagVerified": false, "isModel": true, "isLovense": true, "isKiiroo": false, "doSpy": true, "doPrivate": true, "isAvatarApproved": true}, {"gender": "female", "groupShowType": "", "country": "", "broadcastGender": "female", "avatarUrl": "https://static-cdn.strpst.com/avatars/9/3/1/931fbee59aedfab20585b83f10109e33-full", "genderGroup": "F", "previewUrlThumbBig": "https://static-cdn.strpst.com/previews/3/5/d/35d8107ecbb23b10e019ae9d6a6c3c31-thumb-big", "previewUrlThumbSmall": "https://static-cdn.strpst.com/previews/3/5/d/35d8107ecbb23b10e019ae9d6a6c3c31-thumb-small", "username": "M--I--A", "hlsPlaylist": "https://edge-hls.doppiocdn.com/hls/82290028/master/82290028_240p.m3u8", "snapshotServer": "us23", "status": "public", "snapshotTimestamp": "1690570080", "broadcastSettings": {"width": 1280, "height": 720}, "viewersCount": 64, "topBestPlace": 85, "publicRecordingsRate": 8, "privateRate": 32, "popularSnapshotTimestamp": 1690569570, "spyRate": 60, "p2pRate": 60, "p2pVoiceRate": 0, "id": 82290028, "hasGroupShowAnnouncement": false, "isNonNude": false, "isHd": true, "isVr": false, "isMobile": false, "isNew": false, "isLive": true, "isOnline": true, "isRecommended": false, "isTagVerified": false, "isModel": true, "isLovense": true, "isKiiroo": false, "doSpy": true, "doPrivate": true, "isAvatarApproved": true}, {"gender": "female", "groupShowType": "", "country": "", "broadcastGender": "female", "avatarUrl": "https://static-cdn.strpst.com/avatars/6/2/9/629cecc26e7e5f84cef87cc8ce20b40c-full", "genderGroup": "F", "previewUrlThumbBig": "https://static-cdn.strpst.com/previews/b/5/d/b5d78a1bf2adc9de2f431c289451023c-thumb-big", "previewUrlThumbSmall": "https://static-cdn.strpst.com/previews/b/5/d/b5d78a1bf2adc9de2f431c289451023c-thumb-small", "username": "-Cheese_", "hlsPlaylist": "https://edge-hls.doppiocdn.com/hls/103798948/master/103798948_240p.m3u8", "snapshotServer": "us24", "status": "public", "snapshotTimestamp": "1690570080", "broadcastSettings": {"width": 1280, "height": 720}, "viewersCount": 132, "topBestPlace": 0, "publicRecordingsRate": 150, "privateRate": 60, "popularSnapshotTimestamp": 1690569600, "spyRate": 60, "p2pRate": 90, "p2pVoiceRate": 0, "id": 103798948, "hasGroupShowAnnouncement": false, "isNonNude": false, "isHd": true, "isVr": false, "isMobile": false, "isNew": false, "isLive": true, "isOnline": true, "isRecommended": false, "isTagVerified": false, "isModel": true, "isLovense": true, "isKiiroo": false, "doSpy": true, "doPrivate": true, "isAvatarApproved": true}, {"gender": "female", "groupShowType": "", "country": "", "broadcastGender": "female", "avatarUrl": "https://static-cdn.strpst.com/avatars/7/f/f/7fff682939b39668ff26da2b9d323bf4-full", "genderGroup": "F", "previewUrlThumbBig": "https://static-cdn.strpst.com/previews/f/8/e/f8ea6f0a730d654e41d8e0119b492ca9-thumb-big", "previewUrlThumbSmall": "https://static-cdn.strpst.com/previews/f/8/e/f8ea6f0a730d654e41d8e0119b492ca9-thumb-small", "username": "-SweetNaNa_", "hlsPlaylist": "https://edge-hls.doppiocdn.com/hls/111868433/master/111868433.m3u8", "snapshotServer": "us26", "status": "public", "snapshotTimestamp": "1690570080", "broadcastSettings": {"width": 864, "height": 480}, "viewersCount": 35, "topBestPlace": 0, "publicRecordingsRate": 60, "privateRate": 60, "popularSnapshotTimestamp": 1690569930, "spyRate": 60, "p2pRate": 90, "p2pVoiceRate": 0, "id": 111868433, "hasGroupShowAnnouncement": false, "isNonNude": false, "isHd": false, "isVr": false, "isMobile": false, "isNew": false, "isLive": true, "isOnline": true, "isRecommended": false, "isTagVerified": false, "isModel": true, "isLovense": true, "isKiiroo": false, "doSpy": true, "doPrivate": true, "isAvatarApproved": true}, {"gender": "female", "groupShowType": "", "country": "cn", "broadcastGender": "female", "avatarUrl": "https://static-cdn.strpst.com/avatars/7/e/5/7e572b86540dc4f46c1b31ec8430f536-full", "genderGroup": "F", "previewUrlThumbBig": "https://static-cdn.strpst.com/previews/7/a/6/7a6edfcbd3f463d885c9285450b5e274-thumb-big", "previewUrlThumbSmall": "https://static-cdn.strpst.com/previews/7/a/6/7a6edfcbd3f463d885c9285450b5e274-thumb-small", "username": "uni-cn", "hlsPlaylist": "https://edge-hls.doppiocdn.com/hls/119068224/master/119068224_240p.m3u8", "snapshotServer": "us22", "status": "public", "snapshotTimestamp": "1690570080", "broadcastSettings": {"width": 1280, "height": 720}, "viewersCount": 189, "topBestPlace": 0, "publicRecordingsRate": 150, "privateRate": 90, "popularSnapshotTimestamp": 1690569570, "spyRate": 60, "p2pRate": 120, "p2pVoiceRate": 0, "id": 119068224, "hasGroupShowAnnouncement": false, "isNonNude": false, "isHd": true, "isVr": false, "isMobile": false, "isNew": true, "isLive": true, "isOnline": true, "isRecommended": false, "isTagVerified": false, "isModel": true, "isLovense": true, "isKiiroo": false, "doSpy": true, "doPrivate": true, "isAvatarApproved": true}, {"gender": "female", "groupShowType": "", "country": "", "broadcastGender": "female", "avatarUrl": "https://static-cdn.strpst.com/avatars/7/4/7/74718e57ab81dd3b726ae8276a2fa695-full", "genderGroup": "F", "previewUrlThumbBig": "https://static-cdn.strpst.com/previews/3/0/8/308e886ed4e3119d2311c3448d7c0721-thumb-big", "previewUrlThumbSmall": "https://static-cdn.strpst.com/previews/3/0/8/308e886ed4e3119d2311c3448d7c0721-thumb-small", "username": "ya-Lydia", "hlsPlaylist": "https://edge-hls.doppiocdn.com/hls/77617676/master/77617676.m3u8", "snapshotServer": "us24", "status": "public", "snapshotTimestamp": "1690570080", "broadcastSettings": {"width": 864, "height": 480}, "viewersCount": 58, "topBestPlace": 44, "publicRecordingsRate": 8, "privateRate": 60, "popularSnapshotTimestamp": 1690569570, "spyRate": 60, "p2pRate": 120, "p2pVoiceRate": 0, "id": 77617676, "hasGroupShowAnnouncement": false, "isNonNude": false, "isHd": false, "isVr": false, "isMobile": false, "isNew": false, "isLive": true, "isOnline": true, "isRecommended": false, "isTagVerified": false, "isModel": true, "isLovense": true, "isKiiroo": false, "doSpy": true, "doPrivate": true, "isAvatarApproved": true}, {"gender": "female", "groupShowType": "", "country": "", "broadcastGender": "female", "avatarUrl": "https://static-cdn.strpst.com/avatars/e/b/8/eb8b7c3c7fc075fcfe2a21eab3864f57-full", "genderGroup": "F", "previewUrlThumbBig": "https://static-cdn.strpst.com/previews/9/8/0/980062e2f6117fbab19d60c7bc9e096b-thumb-big", "previewUrlThumbSmall": "https://static-cdn.strpst.com/previews/9/8/0/980062e2f6117fbab19d60c7bc9e096b-thumb-small", "username": "Southerly", "hlsPlaylist": "https://edge-hls.doppiocdn.com/hls/93936177/master/93936177_240p.m3u8", "snapshotServer": "us24", "status": "public", "snapshotTimestamp": "1690570080", "broadcastSettings": {"width": 1280, "height": 720}, "viewersCount": 230, "topBestPlace": 0, "publicRecordingsRate": 150, "privateRate": 60, "popularSnapshotTimestamp": 1690569450, "spyRate": 44, "p2pRate": 90, "p2pVoiceRate": 0, "id": 93936177, "hasGroupShowAnnouncement": false, "isNonNude": false, "isHd": true, "isVr": false, "isMobile": false, "isNew": false, "isLive": true, "isOnline": true, "isRecommended": false, "isTagVerified": false, "isModel": true, "isLovense": true, "isKiiroo": false, "doSpy": true, "doPrivate": true, "isAvatarApproved": true}, {"gender": "female", "groupShowType": "", "country": "", "broadcastGender": "female", "avatarUrl": "https://static-cdn.strpst.com/avatars/b/5/6/b56e506b4b46ba3b9747fd6b504dc049-full", "genderGroup": "F", "previewUrlThumbBig": "https://static-cdn.strpst.com/previews/8/4/5/845f9fcf613ee159bc67918e46c14277-thumb-big", "previewUrlThumbSmall": "https://static-cdn.strpst.com/previews/8/4/5/845f9fcf613ee159bc67918e46c14277-thumb-small", "username": "-youmi-", "hlsPlaylist": "https://edge-hls.doppiocdn.com/hls/121436884/master/121436884_240p.m3u8", "snapshotServer": "us22", "status": "public", "snapshotTimestamp": "1690570080", "broadcastSettings": {"width": 1280, "height": 720}, "viewersCount": 29, "topBestPlace": 0, "publicRecordingsRate": 8, "privateRate": 44, "popularSnapshotTimestamp": 1690569540, "spyRate": 60, "p2pRate": 60, "p2pVoiceRate": 0, "id": 121436884, "hasGroupShowAnnouncement": false, "isNonNude": false, "isHd": true, "isVr": false, "isMobile": false, "isNew": true, "isLive": true, "isOnline": true, "isRecommended": false, "isTagVerified": false, "isModel": true, "isLovense": true, "isKiiroo": false, "doSpy": true, "doPrivate": true, "isAvatarApproved": true}, {"gender": "female", "groupShowType": "", "country": "", "broadcastGender": "female", "avatarUrl": "https://static-cdn.strpst.com/avatars/1/3/8/138d3f8c8d070e2f13e8991f0f72ecb5-full", "genderGroup": "F", "previewUrlThumbBig": "https://static-cdn.strpst.com/previews/1/c/b/1cbd627c1a490bcfc90a75465b84d541-thumb-big", "previewUrlThumbSmall": "https://static-cdn.strpst.com/previews/1/c/b/1cbd627c1a490bcfc90a75465b84d541-thumb-small", "username": "Miaomiao-Nicole", "hlsPlaylist": "https://edge-hls.doppiocdn.com/hls/121789226/master/121789226_240p.m3u8", "snapshotServer": "us26", "status": "public", "snapshotTimestamp": "1690570080", "broadcastSettings": {"width": 1280, "height": 720}, "viewersCount": 33, "topBestPlace": 0, "publicRecordingsRate": 8, "privateRate": 44, "popularSnapshotTimestamp": 1690569540, "spyRate": 32, "p2pRate": 60, "p2pVoiceRate": 0, "id": 121789226, "hasGroupShowAnnouncement": false, "isNonNude": false, "isHd": true, "isVr": false, "isMobile": false, "isNew": true, "isLive": true, "isOnline": true, "isRecommended": false, "isTagVerified": false, "isModel": true, "isLovense": true, "isKiiroo": false, "doSpy": true, "doPrivate": true, "isAvatarApproved": true}, {"gender": "female", "groupShowType": "", "country": "", "broadcastGender": "female", "avatarUrl": "https://static-cdn.strpst.com/avatars/4/2/9/429f8c5ad0d7802bf1ab657a3ecbbe56-full", "genderGroup": "F", "previewUrlThumbBig": "https://static-cdn.strpst.com/previews/4/a/8/4a8522f4ddbcc839cf1676f7e762149a-thumb-big", "previewUrlThumbSmall": "https://static-cdn.strpst.com/previews/4/a/8/4a8522f4ddbcc839cf1676f7e762149a-thumb-small", "username": "Top_Michelle", "hlsPlaylist": "https://edge-hls.doppiocdn.com/hls/103352976/master/103352976_240p.m3u8", "snapshotServer": "us26", "status": "public", "snapshotTimestamp": "1690570080", "broadcastSettings": {"width": 1280, "height": 720}, "viewersCount": 25, "topBestPlace": 0, "publicRecordingsRate": 8, "privateRate": 60, "popularSnapshotTimestamp": 1690569900, "spyRate": 60, "p2pRate": 120, "p2pVoiceRate": 0, "id": 103352976, "hasGroupShowAnnouncement": false, "isNonNude": false, "isHd": true, "isVr": false, "isMobile": false, "isNew": false, "isLive": true, "isOnline": true, "isRecommended": false, "isTagVerified": false, "isModel": true, "isLovense": true, "isKiiroo": false, "doSpy": true, "doPrivate": true, "isAvatarApproved": true}, {"gender": "female", "groupShowType": "", "country": "tw", "broadcastGender": "female", "avatarUrl": "https://static-cdn.strpst.com/avatars/4/2/2/422bdd876d322a4108382d5072e04f46-full", "genderGroup": "F", "previewUrlThumbBig": "https://static-cdn.strpst.com/previews/7/1/5/715f3d56f077f4590d9ee9e954d011d1-thumb-big", "previewUrlThumbSmall": "https://static-cdn.strpst.com/previews/7/1/5/715f3d56f077f4590d9ee9e954d011d1-thumb-small", "username": "Snow_michelle", "hlsPlaylist": "https://edge-hls.doppiocdn.com/hls/121843776/master/121843776_240p.m3u8", "snapshotServer": "", "status": "idle", "snapshotTimestamp": "1690570080", "broadcastSettings": {"width": 1280, "height": 720}, "viewersCount": 18, "topBestPlace": 0, "publicRecordingsRate": 8, "privateRate": 90, "popularSnapshotTimestamp": 0, "spyRate": 60, "p2pRate": 90, "p2pVoiceRate": 0, "id": 121843776, "hasGroupShowAnnouncement": false, "isNonNude": false, "isHd": true, "isVr": false, "isMobile": false, "isNew": true, "isLive": false, "isOnline": true, "isRecommended": false, "isTagVerified": false, "isModel": true, "isLovense": true, "isKiiroo": false, "doSpy": true, "doPrivate": true, "isAvatarApproved": true}, {"gender": "female", "groupShowType": "", "country": "cn", "broadcastGender": "female", "avatarUrl": "https://static-cdn.strpst.com/avatars/6/8/c/68c8db43da5784d86704812efe891960-full", "genderGroup": "F", "previewUrlThumbBig": "https://static-cdn.strpst.com/previews/b/b/4/bb45bee4452ce1aeeecd39c456e8eb39-thumb-big", "previewUrlThumbSmall": "https://static-cdn.strpst.com/previews/b/b/4/bb45bee4452ce1aeeecd39c456e8eb39-thumb-small", "username": "Qiu_Kiyomi", "hlsPlaylist": "https://edge-hls.doppiocdn.com/hls/118481959/master/118481959_240p.m3u8", "snapshotServer": "us25", "status": "public", "snapshotTimestamp": "1690570080", "broadcastSettings": {"width": 1280, "height": 720}, "viewersCount": 572, "topBestPlace": 0, "publicRecordingsRate": 24, "privateRate": 60, "popularSnapshotTimestamp": 1690569570, "spyRate": 32, "p2pRate": 90, "p2pVoiceRate": 0, "id": 118481959, "hasGroupShowAnnouncement": false, "isNonNude": false, "isHd": true, "isVr": false, "isMobile": false, "isNew": false, "isLive": true, "isOnline": true, "isRecommended": false, "isTagVerified": false, "isModel": true, "isLovense": true, "isKiiroo": false, "doSpy": true, "doPrivate": true, "isAvatarApproved": true}, {"gender": "female", "groupShowType": "", "country": "", "broadcastGender": "female", "avatarUrl": "https://static-cdn.strpst.com/avatars/9/9/e/99eda82d8db0b53c08b36ff919c59415-full", "genderGroup": "F", "previewUrlThumbBig": "https://static-cdn.strpst.com/previews/7/1/a/71accae0093f6da2fc4609f68fd7bd54-thumb-big", "previewUrlThumbSmall": "https://static-cdn.strpst.com/previews/7/1/a/71accae0093f6da2fc4609f68fd7bd54-thumb-small", "username": "Sweets-Baby", "hlsPlaylist": "https://edge-hls.doppiocdn.com/hls/121922601/master/121922601_240p.m3u8", "snapshotServer": "us23", "status": "public", "snapshotTimestamp": "1690570080", "broadcastSettings": {"width": 1280, "height": 720}, "viewersCount": 20, "topBestPlace": 0, "publicRecordingsRate": 8, "privateRate": 60, "popularSnapshotTimestamp": 1690569270, "spyRate": 60, "p2pRate": 120, "p2pVoiceRate": 0, "id": 121922601, "hasGroupShowAnnouncement": false, "isNonNude": false, "isHd": true, "isVr": false, "isMobile": false, "isNew": true, "isLive": true, "isOnline": true, "isRecommended": false, "isTagVerified": false, "isModel": true, "isLovense": true, "isKiiroo": false, "doSpy": true, "doPrivate": true, "isAvatarApproved": true}, {"gender": "females", "groupShowType": "", "country": "", "broadcastGender": "female", "avatarUrl": "https://static-cdn.strpst.com/avatars/e/7/4/e7400d4cf1ec7b3e1dfdff5ac395141a-full", "genderGroup": "F", "previewUrlThumbBig": "https://static-cdn.strpst.com/previews/5/e/f/5efe066f0370486f365dc329f6b2c409-thumb-big", "previewUrlThumbSmall": "https://static-cdn.strpst.com/previews/5/e/f/5efe066f0370486f365dc329f6b2c409-thumb-small", "username": "sm-Yingzi", "hlsPlaylist": "https://edge-hls.doppiocdn.com/hls/107261554/master/107261554_240p.m3u8", "snapshotServer": "us22", "status": "public", "snapshotTimestamp": "1690570080", "broadcastSettings": {"width": 1280, "height": 720}, "viewersCount": 140, "topBestPlace": 0, "publicRecordingsRate": 12, "privateRate": 60, "popularSnapshotTimestamp": 1690569390, "spyRate": 44, "p2pRate": 90, "p2pVoiceRate": 0, "id": 107261554, "hasGroupShowAnnouncement": false, "isNonNude": false, "isHd": true, "isVr": false, "isMobile": false, "isNew": false, "isLive": true, "isOnline": true, "isRecommended": false, "isTagVerified": false, "isModel": true, "isLovense": true, "isKiiroo": false, "doSpy": true, "doPrivate": true, "isAvatarApproved": true}, {"gender": "female", "groupShowType": "", "country": "", "broadcastGender": "female", "avatarUrl": "https://static-cdn.strpst.com/avatars/9/2/2/9229973028fc13387fb5fcfbd883df19-full", "genderGroup": "F", "previewUrlThumbBig": "https://static-cdn.strpst.com/previews/1/f/0/1f04ff46d18be168e7c398025565d93d-thumb-big", "previewUrlThumbSmall": "https://static-cdn.strpst.com/previews/1/f/0/1f04ff46d18be168e7c398025565d93d-thumb-small", "username": "ToP--LuLu", "hlsPlaylist": "https://edge-hls.doppiocdn.com/hls/97045924/master/97045924_240p.m3u8", "snapshotServer": "us23", "status": "public", "snapshotTimestamp": "1690570080", "broadcastSettings": {"width": 1440, "height": 810}, "viewersCount": 53, "topBestPlace": 0, "publicRecordingsRate": 8, "privateRate": 60, "popularSnapshotTimestamp": 1690569390, "spyRate": 0, "p2pRate": 120, "p2pVoiceRate": 0, "id": 97045924, "hasGroupShowAnnouncement": false, "isNonNude": false, "isHd": true, "isVr": false, "isMobile": false, "isNew": false, "isLive": true, "isOnline": true, "isRecommended": false, "isTagVerified": false, "isModel": true, "isLovense": true, "isKiiroo": false, "doSpy": false, "doPrivate": true, "isAvatarApproved": true}, {"gender": "female", "groupShowType": "", "country": "", "broadcastGender": "female", "genderGroup": "F", "previewUrlThumbBig": "https://static-cdn.strpst.com/previews/7/a/d/7ad33af15e648816e1d2d79fb98f280a-thumb-big", "previewUrlThumbSmall": "https://static-cdn.strpst.com/previews/7/a/d/7ad33af15e648816e1d2d79fb98f280a-thumb-small", "username": "Toochache", "hlsPlaylist": "https://edge-hls.doppiocdn.com/hls/111240962/master/111240962_240p.m3u8", "snapshotServer": "us25", "status": "public", "snapshotTimestamp": "1690570080", "broadcastSettings": {"width": 1280, "height": 720}, "viewersCount": 31, "topBestPlace": 0, "publicRecordingsRate": 8, "privateRate": 44, "popularSnapshotTimestamp": 1690569540, "spyRate": 0, "p2pRate": 60, "p2pVoiceRate": 0, "id": 111240962, "hasGroupShowAnnouncement": false, "isNonNude": false, "isHd": true, "isVr": false, "isMobile": false, "isNew": false, "isLive": true, "isOnline": true, "isRecommended": false, "isTagVerified": false, "isModel": true, "isLovense": false, "isKiiroo": false, "doSpy": false, "doPrivate": true}, {"gender": "female", "groupShowType": "", "country": "cn", "broadcastGender": "female", "avatarUrl": "https://static-cdn.strpst.com/avatars/e/2/b/e2b90446742eabcda1e3f4c4f65d2c32-full", "genderGroup": "F", "previewUrlThumbBig": "https://static-cdn.strpst.com/previews/f/3/d/f3d0162c0941f3825dec0df1e2124947-thumb-big", "previewUrlThumbSmall": "https://static-cdn.strpst.com/previews/f/3/d/f3d0162c0941f3825dec0df1e2124947-thumb-small", "username": "veronica88", "hlsPlaylist": "https://edge-hls.doppiocdn.com/hls/113376522/master/113376522_240p.m3u8", "snapshotServer": "us24", "status": "public", "snapshotTimestamp": "1690570080", "broadcastSettings": {"width": 1280, "height": 720}, "viewersCount": 110, "topBestPlace": 0, "publicRecordingsRate": 8, "privateRate": 60, "popularSnapshotTimestamp": 1690569540, "spyRate": 60, "p2pRate": 120, "p2pVoiceRate": 0, "id": 113376522, "hasGroupShowAnnouncement": false, "isNonNude": false, "isHd": true, "isVr": false, "isMobile": false, "isNew": false, "isLive": true, "isOnline": true, "isRecommended": false, "isTagVerified": false, "isModel": true, "isLovense": true, "isKiiroo": false, "doSpy": true, "doPrivate": true, "isAvatarApproved": true}, {"gender": "female", "groupShowType": "", "country": "", "broadcastGender": "female", "avatarUrl": "https://static-cdn.strpst.com/avatars/1/0/5/105afa71b724381d083556851a2f6f54-full", "genderGroup": "F", "previewUrlThumbBig": "https://static-cdn.strpst.com/previews/c/5/e/c5ed3ffe35a9214773a165422a150a9e-thumb-big", "previewUrlThumbSmall": "https://static-cdn.strpst.com/previews/c/5/e/c5ed3ffe35a9214773a165422a150a9e-thumb-small", "username": "xiaoluoli-6", "hlsPlaylist": "https://edge-hls.doppiocdn.com/hls/121116049/master/121116049_240p.m3u8", "snapshotServer": "us24", "status": "public", "snapshotTimestamp": "1690570080", "broadcastSettings": {"width": 1280, "height": 720}, "viewersCount": 95, "topBestPlace": 0, "publicRecordingsRate": 90, "privateRate": 60, "popularSnapshotTimestamp": 1690569780, "spyRate": 32, "p2pRate": 60, "p2pVoiceRate": 0, "id": 121116049, "hasGroupShowAnnouncement": false, "isNonNude": false, "isHd": true, "isVr": false, "isMobile": false, "isNew": true, "isLive": true, "isOnline": true, "isRecommended": false, "isTagVerified": false, "isModel": true, "isLovense": true, "isKiiroo": false, "doSpy": true, "doPrivate": true, "isAvatarApproved": true}, {"gender": "female", "groupShowType": "", "country": "", "broadcastGender": "female", "avatarUrl": "https://static-cdn.strpst.com/avatars/6/a/d/6ade2a52aa8055d83ac008e4d47128c2-full", "genderGroup": "F", "previewUrlThumbBig": "https://static-cdn.strpst.com/previews/f/2/6/f26db459200a4505c722a840c18f2c74-thumb-big", "previewUrlThumbSmall": "https://static-cdn.strpst.com/previews/f/2/6/f26db459200a4505c722a840c18f2c74-thumb-small", "username": "Amelia_ava_", "hlsPlaylist": "https://edge-hls.doppiocdn.com/hls/114789082/master/114789082_240p.m3u8", "snapshotServer": "us25", "status": "public", "snapshotTimestamp": "1690570080", "broadcastSettings": {"width": 1280, "height": 720}, "viewersCount": 19, "topBestPlace": 0, "publicRecordingsRate": 8, "privateRate": 44, "popularSnapshotTimestamp": 1690569930, "spyRate": 60, "p2pRate": 90, "p2pVoiceRate": 0, "id": 114789082, "hasGroupShowAnnouncement": false, "isNonNude": false, "isHd": true, "isVr": false, "isMobile": false, "isNew": false, "isLive": true, "isOnline": true, "isRecommended": false, "isTagVerified": false, "isModel": true, "isLovense": true, "isKiiroo": false, "doSpy": true, "doPrivate": true}, {"gender": "female", "groupShowType": "", "country": "", "broadcastGender": "female", "avatarUrl": "https://static-cdn.strpst.com/avatars/9/6/e/96ee9b8573a1e1af267a6cac61dd6db7-full", "genderGroup": "F", "previewUrlThumbBig": "https://static-cdn.strpst.com/previews/b/1/1/b11ab783c08a2875413c6eb503f76fce-thumb-big", "previewUrlThumbSmall": "https://static-cdn.strpst.com/previews/b/1/1/b11ab783c08a2875413c6eb503f76fce-thumb-small", "username": "18-JessX", "hlsPlaylist": "https://edge-hls.doppiocdn.com/hls/111141447/master/111141447_240p.m3u8", "snapshotServer": "us23", "status": "public", "snapshotTimestamp": "1690570080", "broadcastSettings": {"width": 1280, "height": 720}, "viewersCount": 43, "topBestPlace": 0, "publicRecordingsRate": 8, "privateRate": 44, "popularSnapshotTimestamp": 0, "spyRate": 60, "p2pRate": 90, "p2pVoiceRate": 0, "id": 111141447, "hasGroupShowAnnouncement": false, "isNonNude": false, "isHd": true, "isVr": false, "isMobile": false, "isNew": false, "isLive": true, "isOnline": true, "isRecommended": false, "isTagVerified": false, "isModel": true, "isLovense": true, "isKiiroo": false, "doSpy": true, "doPrivate": true, "isAvatarApproved": true}, {"gender": "female", "groupShowType": "", "country": "", "broadcastGender": "female", "avatarUrl": "https://static-cdn.strpst.com/avatars/5/d/7/5d760b3e327e3798bd1f1b576ba411b0-full", "genderGroup": "F", "previewUrlThumbBig": "https://static-cdn.strpst.com/previews/7/c/1/7c105955795f70c54037e3654d04455f-thumb-big", "previewUrlThumbSmall": "https://static-cdn.strpst.com/previews/7/c/1/7c105955795f70c54037e3654d04455f-thumb-small", "username": "24-Lexi", "hlsPlaylist": "https://edge-hls.doppiocdn.com/hls/118551799/master/118551799_240p.m3u8", "snapshotServer": "us24", "status": "public", "snapshotTimestamp": "1690570080", "broadcastSettings": {"width": 1280, "height": 720}, "viewersCount": 132, "topBestPlace": 0, "publicRecordingsRate": 8, "privateRate": 44, "popularSnapshotTimestamp": 1690569960, "spyRate": 60, "p2pRate": 90, "p2pVoiceRate": 0, "id": 118551799, "hasGroupShowAnnouncement": false, "isNonNude": false, "isHd": true, "isVr": false, "isMobile": false, "isNew": false, "isLive": true, "isOnline": true, "isRecommended": false, "isTagVerified": false, "isModel": true, "isLovense": true, "isKiiroo": false, "doSpy": true, "doPrivate": true, "isAvatarApproved": true}, {"gender": "female", "groupShowType": "", "country": "", "broadcastGender": "female", "avatarUrl": "https://static-cdn.strpst.com/avatars/e/f/4/ef481d527c44a9887fa6494474477091-full", "genderGroup": "F", "previewUrlThumbBig": "https://static-cdn.strpst.com/previews/d/5/7/d57faa4adf7e7faa2260e702910dd883-thumb-big", "previewUrlThumbSmall": "https://static-cdn.strpst.com/previews/d/5/7/d57faa4adf7e7faa2260e702910dd883-thumb-small", "username": "Lucker-", "hlsPlaylist": "https://edge-hls.doppiocdn.com/hls/117733879/master/117733879_240p.m3u8", "snapshotServer": "us25", "status": "public", "snapshotTimestamp": "1690570080", "broadcastSettings": {"width": 1920, "height": 1080}, "viewersCount": 59, "topBestPlace": 0, "publicRecordingsRate": 8, "privateRate": 32, "popularSnapshotTimestamp": 1690569660, "spyRate": 44, "p2pRate": 90, "p2pVoiceRate": 0, "id": 117733879, "hasGroupShowAnnouncement": false, "isNonNude": false, "isHd": true, "isVr": false, "isMobile": false, "isNew": false, "isLive": true, "isOnline": true, "isRecommended": false, "isTagVerified": false, "isModel": true, "isLovense": true, "isKiiroo": false, "doSpy": true, "doPrivate": true, "isAvatarApproved": true}, {"gender": "female", "groupShowType": "", "country": "cn", "broadcastGender": "female", "avatarUrl": "https://static-cdn.strpst.com/avatars/e/5/f/e5fc90b5374fc74b6de6dc88f73538ec-full", "genderGroup": "F", "previewUrlThumbBig": "https://static-cdn.strpst.com/previews/2/d/4/2d4033eacc51a1dbbc48228070d682a0-thumb-big", "previewUrlThumbSmall": "https://static-cdn.strpst.com/previews/2/d/4/2d4033eacc51a1dbbc48228070d682a0-thumb-small", "username": "JennyKnight", "hlsPlaylist": "https://edge-hls.doppiocdn.com/hls/111756915/master/111756915_240p.m3u8", "snapshotServer": "us23", "status": "public", "snapshotTimestamp": "1690570080", "broadcastSettings": {"width": 1280, "height": 720}, "viewersCount": 54, "topBestPlace": 0, "publicRecordingsRate": 8, "privateRate": 44, "popularSnapshotTimestamp": 1690569450, "spyRate": 60, "p2pRate": 60, "p2pVoiceRate": 0, "id": 111756915, "hasGroupShowAnnouncement": false, "isNonNude": false, "isHd": true, "isVr": false, "isMobile": false, "isNew": false, "isLive": true, "isOnline": true, "isRecommended": false, "isTagVerified": false, "isModel": true, "isLovense": true, "isKiiroo": false, "doSpy": true, "doPrivate": true, "isAvatarApproved": true}, {"gender": "female", "groupShowType": "", "country": "", "broadcastGender": "female", "avatarUrl": "https://static-cdn.strpst.com/avatars/3/0/d/30d10a0e0c36d2b4f8098b29c0778c26-full", "genderGroup": "F", "previewUrlThumbBig": "https://static-cdn.strpst.com/previews/7/e/7/7e734d414fae3e16ff6a748cd847e06a-thumb-big", "previewUrlThumbSmall": "https://static-cdn.strpst.com/previews/7/e/7/7e734d414fae3e16ff6a748cd847e06a-thumb-small", "username": "Alyssa_520", "hlsPlaylist": "https://edge-hls.doppiocdn.com/hls/114899382/master/114899382_240p.m3u8", "snapshotServer": "us24", "status": "public", "snapshotTimestamp": "1690570080", "broadcastSettings": {"width": 1280, "height": 720}, "viewersCount": 139, "topBestPlace": 0, "publicRecordingsRate": 8, "privateRate": 60, "popularSnapshotTimestamp": 1690569450, "spyRate": 44, "p2pRate": 90, "p2pVoiceRate": 0, "id": 114899382, "hasGroupShowAnnouncement": false, "isNonNude": false, "isHd": true, "isVr": false, "isMobile": false, "isNew": false, "isLive": true, "isOnline": true, "isRecommended": false, "isTagVerified": false, "isModel": true, "isLovense": true, "isKiiroo": false, "doSpy": true, "doPrivate": true, "isAvatarApproved": true}, {"gender": "female", "groupShowType": "", "country": "", "broadcastGender": "female", "avatarUrl": "https://static-cdn.strpst.com/avatars/6/8/c/68c0be0bf1dd2b78f751d45389c5ef9b-full", "genderGroup": "F", "previewUrlThumbBig": "https://static-cdn.strpst.com/previews/d/9/1/d911904675e740053f4eb4e7f65db39d-thumb-big", "previewUrlThumbSmall": "https://static-cdn.strpst.com/previews/d/9/1/d911904675e740053f4eb4e7f65db39d-thumb-small", "username": "Bunny_Alysa", "hlsPlaylist": "https://edge-hls.doppiocdn.com/hls/79132216/master/79132216_240p.m3u8", "snapshotServer": "us24", "status": "public", "snapshotTimestamp": "1690570080", "broadcastSettings": {"width": 1280, "height": 720}, "viewersCount": 7, "topBestPlace": 0, "publicRecordingsRate": 8, "privateRate": 32, "popularSnapshotTimestamp": 1690569420, "spyRate": 60, "p2pRate": 90, "p2pVoiceRate": 0, "id": 79132216, "hasGroupShowAnnouncement": false, "isNonNude": false, "isHd": true, "isVr": false, "isMobile": false, "isNew": false, "isLive": true, "isOnline": true, "isRecommended": false, "isTagVerified": false, "isModel": true, "isLovense": false, "isKiiroo": false, "doSpy": true, "doPrivate": true, "isAvatarApproved": true}, {"gender": "females", "groupShowType": "", "country": "cn", "broadcastGender": "group", "avatarUrl": "https://static-cdn.strpst.com/avatars/2/4/e/24e88e4cc3ddef5ac064b339f06b1954-full", "genderGroup": "F", "previewUrlThumbBig": "https://static-cdn.strpst.com/previews/2/7/c/27cad6841152358d8129e99722c11815-thumb-big", "previewUrlThumbSmall": "https://static-cdn.strpst.com/previews/2/7/c/27cad6841152358d8129e99722c11815-thumb-small", "username": "QiuPeiPeimmm", "hlsPlaylist": "https://edge-hls.doppiocdn.com/hls/84195834/master/84195834.m3u8", "snapshotServer": "us24", "status": "public", "snapshotTimestamp": "1690570080", "broadcastSettings": {"width": 864, "height": 480}, "viewersCount": 49, "topBestPlace": 0, "publicRecordingsRate": 32, "privateRate": 60, "popularSnapshotTimestamp": 1690569960, "spyRate": 60, "p2pRate": 90, "p2pVoiceRate": 0, "id": 84195834, "hasGroupShowAnnouncement": false, "isNonNude": false, "isHd": false, "isVr": false, "isMobile": false, "isNew": false, "isLive": true, "isOnline": true, "isRecommended": false, "isTagVerified": false, "isModel": true, "isLovense": true, "isKiiroo": false, "doSpy": true, "doPrivate": true, "isAvatarApproved": true}, {"gender": "female", "groupShowType": "", "country": "cn", "broadcastGender": "female", "avatarUrl": "https://static-cdn.strpst.com/avatars/4/6/a/46a0d8e9dddb6b34ff110ec054b262de-full", "genderGroup": "F", "previewUrlThumbBig": "https://static-cdn.strpst.com/previews/e/f/9/ef94cd393160d5c5028f560d921a1da9-thumb-big", "previewUrlThumbSmall": "https://static-cdn.strpst.com/previews/e/f/9/ef94cd393160d5c5028f560d921a1da9-thumb-small", "username": "HelenThorn", "hlsPlaylist": "https://edge-hls.doppiocdn.com/hls/61066097/master/61066097.m3u8", "snapshotServer": "us22", "status": "public", "snapshotTimestamp": "1690570080", "broadcastSettings": {"width": 864, "height": 480}, "viewersCount": 7, "topBestPlace": 0, "publicRecordingsRate": 8, "privateRate": 32, "popularSnapshotTimestamp": 0, "spyRate": 8, "p2pRate": 60, "p2pVoiceRate": 0, "id": 61066097, "hasGroupShowAnnouncement": false, "isNonNude": false, "isHd": false, "isVr": false, "isMobile": false, "isNew": false, "isLive": true, "isOnline": true, "isRecommended": false, "isTagVerified": false, "isModel": true, "isLovense": true, "isKiiroo": false, "doSpy": true, "doPrivate": true, "isAvatarApproved": true}, {"gender": "female", "groupShowType": "", "country": "cn", "broadcastGender": "female", "avatarUrl": "https://static-cdn.strpst.com/avatars/7/c/8/7c8ff9e2f3c021ae6a016f508766a2a3-full", "genderGroup": "F", "previewUrlThumbBig": "https://static-cdn.strpst.com/previews/c/4/7/c47e9530c5620d279d87ee37396fa42b-thumb-big", "previewUrlThumbSmall": "https://static-cdn.strpst.com/previews/c/4/7/c47e9530c5620d279d87ee37396fa42b-thumb-small", "username": "YaniraLove", "hlsPlaylist": "https://edge-hls.doppiocdn.com/hls/117043947/master/117043947_240p.m3u8", "snapshotServer": "us23", "status": "public", "snapshotTimestamp": "1690570080", "broadcastSettings": {"width": 1280, "height": 720}, "viewersCount": 16, "topBestPlace": 0, "publicRecordingsRate": 8, "privateRate": 60, "popularSnapshotTimestamp": 1690569930, "spyRate": 32, "p2pRate": 90, "p2pVoiceRate": 0, "id": 117043947, "hasGroupShowAnnouncement": false, "isNonNude": false, "isHd": true, "isVr": false, "isMobile": false, "isNew": true, "isLive": true, "isOnline": true, "isRecommended": false, "isTagVerified": false, "isModel": true, "isLovense": true, "isKiiroo": false, "doSpy": true, "doPrivate": true, "isAvatarApproved": true}, {"gender": "females", "groupShowType": "", "country": "", "broadcastGender": "female", "avatarUrl": "https://static-cdn.strpst.com/avatars/2/7/f/27f0cd47953dea83819d66809b81a1eb-full", "genderGroup": "F", "previewUrlThumbBig": "https://static-cdn.strpst.com/previews/0/3/d/03d1732b9c664c7cf0413b3291a55844-thumb-big", "previewUrlThumbSmall": "https://static-cdn.strpst.com/previews/0/3/d/03d1732b9c664c7cf0413b3291a55844-thumb-small", "username": "Na_Bii_2k", "hlsPlaylist": "https://edge-hls.doppiocdn.com/hls/109567225/master/109567225.m3u8", "snapshotServer": "us26", "status": "public", "snapshotTimestamp": "1690570080", "broadcastSettings": {"width": 640, "height": 480}, "viewersCount": 30, "topBestPlace": 0, "publicRecordingsRate": 16, "privateRate": 24, "popularSnapshotTimestamp": 1690569660, "spyRate": 32, "p2pRate": 32, "p2pVoiceRate": 0, "id": 109567225, "hasGroupShowAnnouncement": false, "isNonNude": false, "isHd": false, "isVr": false, "isMobile": false, "isNew": false, "isLive": true, "isOnline": true, "isRecommended": false, "isTagVerified": false, "isModel": true, "isLovense": true, "isKiiroo": false, "doSpy": true, "doPrivate": true, "isAvatarApproved": true}, {"gender": "female", "groupShowType": "", "country": "cn", "broadcastGender": "female", "avatarUrl": "https://static-cdn.strpst.com/avatars/f/6/1/f61283c423f1bdec0ea62b9682f038c6-full", "genderGroup": "F", "previewUrlThumbBig": "https://static-cdn.strpst.com/previews/4/a/a/4aa00164b910ed662603de5628b589a4-thumb-big", "previewUrlThumbSmall": "https://static-cdn.strpst.com/previews/4/a/a/4aa00164b910ed662603de5628b589a4-thumb-small", "username": "LULU_22years_old", "hlsPlaylist": "https://edge-hls.doppiocdn.com/hls/116390022/master/116390022.m3u8", "snapshotServer": "us25", "status": "public", "snapshotTimestamp": "1690570080", "broadcastSettings": {"width": 864, "height": 480}, "viewersCount": 43, "topBestPlace": 0, "publicRecordingsRate": 90, "privateRate": 60, "popularSnapshotTimestamp": 1690569570, "spyRate": 60, "p2pRate": 90, "p2pVoiceRate": 0, "id": 116390022, "hasGroupShowAnnouncement": false, "isNonNude": false, "isHd": false, "isVr": false, "isMobile": false, "isNew": false, "isLive": true, "isOnline": true, "isRecommended": false, "isTagVerified": false, "isModel": true, "isLovense": true, "isKiiroo": false, "doSpy": true, "doPrivate": true, "isAvatarApproved": true}, {"gender": "female", "groupShowType": "", "country": "", "broadcastGender": "female", "avatarUrl": "https://static-cdn.strpst.com/avatars/b/1/0/b10352ec3a10595e74aa1404d683c022-full", "genderGroup": "F", "previewUrlThumbBig": "https://static-cdn.strpst.com/previews/4/5/c/45cceb59bed8717e46986ed8e07ea9ae-thumb-big", "previewUrlThumbSmall": "https://static-cdn.strpst.com/previews/4/5/c/45cceb59bed8717e46986ed8e07ea9ae-thumb-small", "username": "S-GIRL", "hlsPlaylist": "https://edge-hls.doppiocdn.com/hls/81805914/master/81805914_240p.m3u8", "snapshotServer": "us25", "status": "public", "snapshotTimestamp": "1690570080", "broadcastSettings": {"width": 1280, "height": 720}, "viewersCount": 52, "topBestPlace": 0, "publicRecordingsRate": 8, "privateRate": 60, "popularSnapshotTimestamp": 1690569300, "spyRate": 60, "p2pRate": 90, "p2pVoiceRate": 0, "id": 81805914, "hasGroupShowAnnouncement": false, "isNonNude": false, "isHd": true, "isVr": false, "isMobile": false, "isNew": false, "isLive": true, "isOnline": true, "isRecommended": false, "isTagVerified": false, "isModel": true, "isLovense": true, "isKiiroo": false, "doSpy": true, "doPrivate": true, "isAvatarApproved": true}, {"gender": "female", "groupShowType": "", "country": "", "broadcastGender": "female", "avatarUrl": "https://static-cdn.strpst.com/avatars/c/7/9/c79adff9adcc7c912e809ebda14b4016-full", "genderGroup": "F", "previewUrlThumbBig": "https://static-cdn.strpst.com/previews/8/a/1/8a13725986727be10642b321b174d3c8-thumb-big", "previewUrlThumbSmall": "https://static-cdn.strpst.com/previews/8/a/1/8a13725986727be10642b321b174d3c8-thumb-small", "username": "YouYou_88", "hlsPlaylist": "https://edge-hls.doppiocdn.com/hls/119470493/master/119470493_240p.m3u8", "snapshotServer": "us25", "status": "public", "snapshotTimestamp": "1690570080", "broadcastSettings": {"width": 1280, "height": 720}, "viewersCount": 43, "topBestPlace": 0, "publicRecordingsRate": 120, "privateRate": 60, "popularSnapshotTimestamp": 1690569840, "spyRate": 60, "p2pRate": 90, "p2pVoiceRate": 0, "id": 119470493, "hasGroupShowAnnouncement": false, "isNonNude": false, "isHd": true, "isVr": false, "isMobile": false, "isNew": false, "isLive": true, "isOnline": true, "isRecommended": false, "isTagVerified": false, "isModel": true, "isLovense": true, "isKiiroo": false, "doSpy": true, "doPrivate": true, "isAvatarApproved": true}, {"gender": "female", "groupShowType": "", "country": "", "broadcastGender": "female", "avatarUrl": "https://static-cdn.strpst.com/avatars/d/4/b/d4b0fdf3751f3e550f37b210f78e011e-full", "genderGroup": "F", "previewUrlThumbBig": "https://static-cdn.strpst.com/previews/4/f/3/4f3a7b74a3c0b7df21dd89d7137e374a-thumb-big", "previewUrlThumbSmall": "https://static-cdn.strpst.com/previews/4/f/3/4f3a7b74a3c0b7df21dd89d7137e374a-thumb-small", "username": "XiaoSanX7", "hlsPlaylist": "https://edge-hls.doppiocdn.com/hls/113137081/master/113137081_240p.m3u8", "snapshotServer": "us25", "status": "public", "snapshotTimestamp": "1690570080", "broadcastSettings": {"width": 1280, "height": 720}, "viewersCount": 26, "topBestPlace": 0, "publicRecordingsRate": 8, "privateRate": 60, "popularSnapshotTimestamp": 1690569720, "spyRate": 60, "p2pRate": 90, "p2pVoiceRate": 0, "id": 113137081, "hasGroupShowAnnouncement": false, "isNonNude": false, "isHd": true, "isVr": false, "isMobile": false, "isNew": false, "isLive": true, "isOnline": true, "isRecommended": false, "isTagVerified": false, "isModel": true, "isLovense": true, "isKiiroo": false, "doSpy": true, "doPrivate": true, "isAvatarApproved": true}, {"gender": "females", "groupShowType": "ticket", "country": "", "broadcastGender": "group", "avatarUrl": "https://static-cdn.strpst.com/avatars/6/9/6/69694e8c41cf2aefec6a80c9423c279f-full", "genderGroup": "F", "previewUrlThumbBig": "https://static-cdn.strpst.com/previews/2/9/a/29ab738aa615ffaa4944ef26e03db4b8-thumb-big", "previewUrlThumbSmall": "https://static-cdn.strpst.com/previews/2/9/a/29ab738aa615ffaa4944ef26e03db4b8-thumb-small", "username": "lrina", "hlsPlaylist": "https://edge-hls.doppiocdn.com/hls/119648784/master/119648784_240p.m3u8", "snapshotServer": "us24", "status": "groupShow", "snapshotTimestamp": "1690570080", "broadcastSettings": {"width": 1280, "height": 720}, "viewersCount": 21, "topBestPlace": 0, "publicRecordingsRate": 8, "privateRate": 60, "popularSnapshotTimestamp": 1690569870, "spyRate": 12, "p2pRate": 120, "p2pVoiceRate": 0, "id": 119648784, "hasGroupShowAnnouncement": false, "isNonNude": false, "isHd": true, "isVr": false, "isMobile": false, "isNew": false, "isLive": true, "isOnline": true, "isRecommended": false, "isTagVerified": false, "isModel": true, "isLovense": true, "isKiiroo": false, "doSpy": true, "doPrivate": true, "isAvatarApproved": true}, {"gender": "female", "groupShowType": "", "country": "", "broadcastGender": "female", "avatarUrl": "https://static-cdn.strpst.com/avatars/5/f/e/5fec34ab409ad5e9506be11d01e32b08-full", "genderGroup": "F", "previewUrlThumbBig": "https://static-cdn.strpst.com/previews/5/a/6/5a62f6ebd09df89c1d577ffb8063accd-thumb-big", "previewUrlThumbSmall": "https://static-cdn.strpst.com/previews/5/a/6/5a62f6ebd09df89c1d577ffb8063accd-thumb-small", "username": "MissChan", "hlsPlaylist": "https://edge-hls.doppiocdn.com/hls/105649637/master/105649637_240p.m3u8", "snapshotServer": "us24", "status": "public", "snapshotTimestamp": "1690570080", "broadcastSettings": {"width": 1280, "height": 720}, "viewersCount": 15, "topBestPlace": 0, "publicRecordingsRate": 8, "privateRate": 44, "popularSnapshotTimestamp": 0, "spyRate": 60, "p2pRate": 90, "p2pVoiceRate": 0, "id": 105649637, "hasGroupShowAnnouncement": false, "isNonNude": false, "isHd": true, "isVr": false, "isMobile": false, "isNew": false, "isLive": true, "isOnline": true, "isRecommended": false, "isTagVerified": false, "isModel": true, "isLovense": true, "isKiiroo": false, "doSpy": true, "doPrivate": true, "isAvatarApproved": true}, {"gender": "females", "groupShowType": "", "country": "", "broadcastGender": "female", "avatarUrl": "https://static-cdn.strpst.com/avatars/3/b/e/3be78094f282ea8ee6e636ad8a85bb51-full", "genderGroup": "F", "previewUrlThumbBig": "https://static-cdn.strpst.com/previews/1/a/0/1a0c7ac9d2466ebfcc94feba9d8905e2-thumb-big", "previewUrlThumbSmall": "https://static-cdn.strpst.com/previews/1/a/0/1a0c7ac9d2466ebfcc94feba9d8905e2-thumb-small", "username": "Ana_chan_", "hlsPlaylist": "https://edge-hls.doppiocdn.com/hls/119987949/master/119987949_240p.m3u8", "snapshotServer": "us24", "status": "public", "snapshotTimestamp": "1690570080", "broadcastSettings": {"width": 1280, "height": 720}, "viewersCount": 16, "topBestPlace": 0, "publicRecordingsRate": 60, "privateRate": 32, "popularSnapshotTimestamp": 1690569180, "spyRate": 44, "p2pRate": 32, "p2pVoiceRate": 0, "id": 119987949, "hasGroupShowAnnouncement": false, "isNonNude": false, "isHd": true, "isVr": false, "isMobile": false, "isNew": false, "isLive": true, "isOnline": true, "isRecommended": false, "isTagVerified": false, "isModel": true, "isLovense": true, "isKiiroo": false, "doSpy": true, "doPrivate": true, "isAvatarApproved": true}, {"gender": "female", "groupShowType": "", "country": "cn", "broadcastGender": "female", "avatarUrl": "https://static-cdn.strpst.com/avatars/5/e/5/5e565b533ff6e2836d39c1bdd48d43a0-full", "genderGroup": "F", "previewUrlThumbBig": "https://static-cdn.strpst.com/previews/c/8/d/c8df4b0398997f330f411beb70895a8b-thumb-big", "previewUrlThumbSmall": "https://static-cdn.strpst.com/previews/c/8/d/c8df4b0398997f330f411beb70895a8b-thumb-small", "username": "dmn520", "hlsPlaylist": "https://edge-hls.doppiocdn.com/hls/89105857/master/89105857_240p.m3u8", "snapshotServer": "us25", "status": "public", "snapshotTimestamp": "1690570080", "broadcastSettings": {"width": 1280, "height": 720}, "viewersCount": 19, "topBestPlace": 0, "publicRecordingsRate": 150, "privateRate": 44, "popularSnapshotTimestamp": 1690569690, "spyRate": 8, "p2pRate": 60, "p2pVoiceRate": 0, "id": 89105857, "hasGroupShowAnnouncement": false, "isNonNude": false, "isHd": true, "isVr": false, "isMobile": false, "isNew": false, "isLive": true, "isOnline": true, "isRecommended": false, "isTagVerified": false, "isModel": true, "isLovense": false, "isKiiroo": false, "doSpy": true, "doPrivate": true, "isAvatarApproved": true}, {"gender": "female", "groupShowType": "", "country": "", "broadcastGender": "female", "avatarUrl": "https://static-cdn.strpst.com/avatars/8/4/2/84292a989d3760e525166d78c3860edb-full", "genderGroup": "F", "previewUrlThumbBig": "https://static-cdn.strpst.com/previews/c/c/d/ccd98f869e3ed6ef3b4c7a0a2bec379e-thumb-big", "previewUrlThumbSmall": "https://static-cdn.strpst.com/previews/c/c/d/ccd98f869e3ed6ef3b4c7a0a2bec379e-thumb-small", "username": "Issi-Aoi", "hlsPlaylist": "https://edge-hls.doppiocdn.com/hls/117817198/master/117817198_240p.m3u8", "snapshotServer": "us26", "status": "public", "snapshotTimestamp": "1690570080", "broadcastSettings": {"width": 1280, "height": 720}, "viewersCount": 12, "topBestPlace": 0, "publicRecordingsRate": 8, "privateRate": 44, "popularSnapshotTimestamp": 1690569780, "spyRate": 60, "p2pRate": 90, "p2pVoiceRate": 0, "id": 117817198, "hasGroupShowAnnouncement": false, "isNonNude": false, "isHd": true, "isVr": false, "isMobile": false, "isNew": false, "isLive": true, "isOnline": true, "isRecommended": false, "isTagVerified": false, "isModel": true, "isLovense": false, "isKiiroo": false, "doSpy": true, "doPrivate": true, "isAvatarApproved": true}, {"gender": "female", "groupShowType": "", "country": "", "broadcastGender": "female", "avatarUrl": "https://static-cdn.strpst.com/avatars/6/a/a/6aa13b8fd3d31727db30a8dae1f42152-full", "genderGroup": "F", "previewUrlThumbBig": "https://static-cdn.strpst.com/previews/c/3/a/c3af82dde08121bf55a7c721bb3358d3-thumb-big", "previewUrlThumbSmall": "https://static-cdn.strpst.com/previews/c/3/a/c3af82dde08121bf55a7c721bb3358d3-thumb-small", "username": "LiangNiang", "hlsPlaylist": "https://edge-hls.doppiocdn.com/hls/113413567/master/113413567_240p.m3u8", "snapshotServer": "us26", "status": "public", "snapshotTimestamp": "1690570080", "broadcastSettings": {"width": 1280, "height": 720}, "viewersCount": 15, "topBestPlace": 0, "publicRecordingsRate": 150, "privateRate": 60, "popularSnapshotTimestamp": 1690569180, "spyRate": 60, "p2pRate": 90, "p2pVoiceRate": 0, "id": 113413567, "hasGroupShowAnnouncement": false, "isNonNude": false, "isHd": true, "isVr": false, "isMobile": false, "isNew": false, "isLive": true, "isOnline": true, "isRecommended": false, "isTagVerified": false, "isModel": true, "isLovense": false, "isKiiroo": false, "doSpy": true, "doPrivate": true, "isAvatarApproved": true}, {"gender": "maleFemale", "groupShowType": "", "country": "", "broadcastGender": "group", "avatarUrl": "https://static-cdn.strpst.com/avatars/0/e/f/0ef7d42f70ee17256d5ba2af446f31ee-full", "genderGroup": "F", "previewUrlThumbBig": "https://static-cdn.strpst.com/previews/7/8/3/783c108a260387451c5071fe88b3ce5c-thumb-big", "previewUrlThumbSmall": "https://static-cdn.strpst.com/previews/7/8/3/783c108a260387451c5071fe88b3ce5c-thumb-small", "username": "erjie", "hlsPlaylist": "https://edge-hls.doppiocdn.com/hls/119691873/master/119691873_240p.m3u8", "snapshotServer": "us23", "status": "public", "snapshotTimestamp": "1690570080", "broadcastSettings": {"width": 1280, "height": 720}, "viewersCount": 17, "topBestPlace": 0, "publicRecordingsRate": 150, "privateRate": 32, "popularSnapshotTimestamp": 1690569420, "spyRate": 16, "p2pRate": 44, "p2pVoiceRate": 0, "id": 119691873, "hasGroupShowAnnouncement": false, "isNonNude": false, "isHd": true, "isVr": false, "isMobile": false, "isNew": false, "isLive": true, "isOnline": true, "isRecommended": false, "isTagVerified": false, "isModel": true, "isLovense": false, "isKiiroo": false, "doSpy": true, "doPrivate": true, "isAvatarApproved": true}, {"gender": "female", "groupShowType": "", "country": "", "broadcastGender": "female", "avatarUrl": "https://static-cdn.strpst.com/avatars/e/3/6/e360ac88a02d6c8753d1e8e5285160c9-full", "genderGroup": "F", "previewUrlThumbBig": "https://static-cdn.strpst.com/previews/5/8/c/58cd6d1c2bfc3019cc52624880f1f5b8-thumb-big", "previewUrlThumbSmall": "https://static-cdn.strpst.com/previews/5/8/c/58cd6d1c2bfc3019cc52624880f1f5b8-thumb-small", "username": "ss_xiaoyaya", "hlsPlaylist": "https://edge-hls.doppiocdn.com/hls/113781155/master/113781155_240p.m3u8", "snapshotServer": "us25", "status": "public", "snapshotTimestamp": "1690570080", "broadcastSettings": {"width": 1920, "height": 1080}, "viewersCount": 207, "topBestPlace": 0, "publicRecordingsRate": 150, "privateRate": 60, "popularSnapshotTimestamp": 1690569750, "spyRate": 60, "p2pRate": 120, "p2pVoiceRate": 0, "id": 113781155, "hasGroupShowAnnouncement": false, "isNonNude": false, "isHd": true, "isVr": false, "isMobile": false, "isNew": false, "isLive": true, "isOnline": true, "isRecommended": false, "isTagVerified": false, "isModel": true, "isLovense": true, "isKiiroo": false, "doSpy": true, "doPrivate": true, "isAvatarApproved": true}, {"gender": "female", "groupShowType": "", "country": "cn", "broadcastGender": "female", "avatarUrl": "https://static-cdn.strpst.com/avatars/7/5/4/7540a2046c8bc8e490bbace4ca1ca10e-full", "genderGroup": "F", "previewUrlThumbBig": "https://static-cdn.strpst.com/previews/9/d/b/9dbe13ecc180ab927c5d2c8bebc13719-thumb-big", "previewUrlThumbSmall": "https://static-cdn.strpst.com/previews/9/d/b/9dbe13ecc180ab927c5d2c8bebc13719-thumb-small", "username": "Litte-Ali", "hlsPlaylist": "https://edge-hls.doppiocdn.com/hls/119322171/master/119322171_240p.m3u8", "snapshotServer": "us22", "status": "public", "snapshotTimestamp": "1690570080", "broadcastSettings": {"width": 1280, "height": 720}, "viewersCount": 53, "topBestPlace": 0, "publicRecordingsRate": 120, "privateRate": 60, "popularSnapshotTimestamp": 0, "spyRate": 60, "p2pRate": 90, "p2pVoiceRate": 0, "id": 119322171, "hasGroupShowAnnouncement": false, "isNonNude": false, "isHd": true, "isVr": false, "isMobile": false, "isNew": false, "isLive": true, "isOnline": true, "isRecommended": false, "isTagVerified": false, "isModel": true, "isLovense": true, "isKiiroo": false, "doSpy": true, "doPrivate": true, "isAvatarApproved": true}, {"gender": "female", "groupShowType": "", "country": "", "broadcastGender": "female", "avatarUrl": "https://static-cdn.strpst.com/avatars/7/3/0/7300fe03ee7404023e506947decc7619-full", "genderGroup": "F", "previewUrlThumbBig": "https://static-cdn.strpst.com/previews/a/6/2/a62880dd249b533f0e624fb1ba83c8b0-thumb-big", "previewUrlThumbSmall": "https://static-cdn.strpst.com/previews/a/6/2/a62880dd249b533f0e624fb1ba83c8b0-thumb-small", "username": "qibao77", "hlsPlaylist": "https://edge-hls.doppiocdn.com/hls/77710968/master/77710968_240p.m3u8", "snapshotServer": "us24", "status": "public", "snapshotTimestamp": "1690570080", "broadcastSettings": {"width": 1280, "height": 720}, "viewersCount": 14, "topBestPlace": 0, "publicRecordingsRate": 8, "privateRate": 200, "popularSnapshotTimestamp": 1690569240, "spyRate": 60, "p2pRate": 250, "p2pVoiceRate": 0, "id": 77710968, "hasGroupShowAnnouncement": false, "isNonNude": false, "isHd": true, "isVr": false, "isMobile": false, "isNew": false, "isLive": true, "isOnline": true, "isRecommended": false, "isTagVerified": false, "isModel": true, "isLovense": false, "isKiiroo": false, "doSpy": true, "doPrivate": true, "isAvatarApproved": true}, {"gender": "female", "groupShowType": "", "country": "tw", "broadcastGender": "female", "avatarUrl": "https://static-cdn.strpst.com/avatars/5/d/3/5d301574436678e475a26e25c76c9faf-full", "genderGroup": "F", "previewUrlThumbBig": "https://static-cdn.strpst.com/previews/3/9/5/395e736fc59a44cf500692d5cfefe0ad-thumb-big", "previewUrlThumbSmall": "https://static-cdn.strpst.com/previews/3/9/5/395e736fc59a44cf500692d5cfefe0ad-thumb-small", "username": "Winglet0814", "hlsPlaylist": "https://edge-hls.doppiocdn.com/hls/110806480/master/110806480_240p.m3u8", "snapshotServer": "us25", "status": "public", "snapshotTimestamp": "1690570080", "broadcastSettings": {"width": 1280, "height": 720}, "viewersCount": 25, "topBestPlace": 0, "publicRecordingsRate": 150, "privateRate": 0, "popularSnapshotTimestamp": 1690569210, "spyRate": 0, "p2pRate": 250, "p2pVoiceRate": 0, "id": 110806480, "hasGroupShowAnnouncement": false, "isNonNude": false, "isHd": true, "isVr": false, "isMobile": false, "isNew": false, "isLive": true, "isOnline": true, "isRecommended": false, "isTagVerified": false, "isModel": true, "isLovense": true, "isKiiroo": false, "doSpy": false, "doPrivate": false, "isAvatarApproved": true}, {"gender": "female", "groupShowType": "", "country": "", "broadcastGender": "female", "avatarUrl": "https://static-cdn.strpst.com/avatars/4/f/a/4fa0856fc54f4248e2c7518c0393f5ee-full", "genderGroup": "F", "previewUrlThumbBig": "https://static-cdn.strpst.com/previews/e/7/2/e727737345e11b17a10d8b1ee3d66334-thumb-big", "previewUrlThumbSmall": "https://static-cdn.strpst.com/previews/e/7/2/e727737345e11b17a10d8b1ee3d66334-thumb-small", "username": "xiaoyababy", "hlsPlaylist": "https://edge-hls.doppiocdn.com/hls/120731261/master/120731261_240p.m3u8", "snapshotServer": "us24", "status": "public", "snapshotTimestamp": "1690570080", "broadcastSettings": {"width": 1280, "height": 720}, "viewersCount": 10, "topBestPlace": 0, "publicRecordingsRate": 8, "privateRate": 60, "popularSnapshotTimestamp": 0, "spyRate": 60, "p2pRate": 90, "p2pVoiceRate": 0, "id": 120731261, "hasGroupShowAnnouncement": false, "isNonNude": false, "isHd": true, "isVr": false, "isMobile": false, "isNew": false, "isLive": true, "isOnline": true, "isRecommended": false, "isTagVerified": false, "isModel": true, "isLovense": true, "isKiiroo": false, "doSpy": true, "doPrivate": true, "isAvatarApproved": true}, {"gender": "female", "groupShowType": "", "country": "", "broadcastGender": "female", "avatarUrl": "https://static-cdn.strpst.com/avatars/6/d/0/6d0450bb769e7f0508763abdfa6d8791-full", "genderGroup": "F", "previewUrlThumbBig": "https://static-cdn.strpst.com/previews/3/1/9/31982a4828021fa16fd232e1c7324d37-thumb-big", "previewUrlThumbSmall": "https://static-cdn.strpst.com/previews/3/1/9/31982a4828021fa16fd232e1c7324d37-thumb-small", "username": "tutubao", "hlsPlaylist": "https://edge-hls.doppiocdn.com/hls/111461032/master/111461032_240p.m3u8", "snapshotServer": "us23", "status": "public", "snapshotTimestamp": "1690570080", "broadcastSettings": {"width": 720, "height": 960}, "viewersCount": 13, "topBestPlace": 0, "publicRecordingsRate": 8, "privateRate": 32, "popularSnapshotTimestamp": 1690569660, "spyRate": 8, "p2pRate": 32, "p2pVoiceRate": 0, "id": 111461032, "hasGroupShowAnnouncement": false, "isNonNude": false, "isHd": true, "isVr": false, "isMobile": true, "isNew": false, "isLive": true, "isOnline": true, "isRecommended": false, "isTagVerified": false, "isModel": true, "isLovense": false, "isKiiroo": false, "doSpy": true, "doPrivate": true, "isAvatarApproved": true}, {"gender": "female", "groupShowType": "perMinute", "country": "tw", "broadcastGender": "female", "avatarUrl": "https://static-cdn.strpst.com/avatars/1/8/a/18ac1ecbc082764c9b1dce206e3adca5-full", "genderGroup": "F", "previewUrlThumbBig": "https://static-cdn.strpst.com/previews/7/1/d/71dde44fb426e39b43c3082b02a0c7f8-thumb-big", "previewUrlThumbSmall": "https://static-cdn.strpst.com/previews/7/1/d/71dde44fb426e39b43c3082b02a0c7f8-thumb-small", "username": "new_bbbb", "hlsPlaylist": "https://edge-hls.doppiocdn.com/hls/105376948/master/105376948.m3u8", "snapshotServer": "us22", "status": "groupShow", "snapshotTimestamp": "1690570080", "broadcastSettings": {"width": 640, "height": 480}, "viewersCount": 6, "topBestPlace": 0, "publicRecordingsRate": 8, "privateRate": 0, "popularSnapshotTimestamp": 1690569210, "spyRate": 0, "p2pRate": 60, "p2pVoiceRate": 0, "id": 105376948, "hasGroupShowAnnouncement": false, "isNonNude": false, "isHd": false, "isVr": false, "isMobile": false, "isNew": false, "isLive": true, "isOnline": true, "isRecommended": false, "isTagVerified": false, "isModel": true, "isLovense": false, "isKiiroo": false, "doSpy": false, "doPrivate": false, "isAvatarApproved": true}, {"gender": "female", "groupShowType": "", "country": "cn", "broadcastGender": "female", "avatarUrl": "https://static-cdn.strpst.com/avatars/f/c/c/fcc1f96e63e9fd20fb4262f725fe531f-full", "genderGroup": "F", "previewUrlThumbBig": "https://static-cdn.strpst.com/previews/0/5/7/057dab4b7094544706a68e5d7e26d080-thumb-big", "previewUrlThumbSmall": "https://static-cdn.strpst.com/previews/0/5/7/057dab4b7094544706a68e5d7e26d080-thumb-small", "username": "AliceEwil", "hlsPlaylist": "https://edge-hls.doppiocdn.com/hls/111544601/master/111544601_240p.m3u8", "snapshotServer": "us23", "status": "public", "snapshotTimestamp": "1690570080", "broadcastSettings": {"width": 1280, "height": 720}, "viewersCount": 7, "topBestPlace": 0, "publicRecordingsRate": 90, "privateRate": 60, "popularSnapshotTimestamp": 1690569210, "spyRate": 0, "p2pRate": 90, "p2pVoiceRate": 0, "id": 111544601, "hasGroupShowAnnouncement": false, "isNonNude": false, "isHd": true, "isVr": false, "isMobile": false, "isNew": false, "isLive": true, "isOnline": true, "isRecommended": false, "isTagVerified": false, "isModel": true, "isLovense": true, "isKiiroo": false, "doSpy": false, "doPrivate": true, "isAvatarApproved": true}]